{"data":{"2":{"avgHighPrice":261,"highPriceVolume":10919,"avgLowPrice":255,"lowPriceVolume":6858},"6":{"avgHighPrice":null,"highPriceVolume":0,"avgLowPrice":188702,"lowPriceVolume":1},"8":{"avgHighPrice":199999,"highPriceVolume":1,"avgLowPrice":184208,"lowPriceVolume":2},"10":{"avgHighPrice":170393,"highPriceVolume":2,"avgLowPrice":162427,"lowPriceVolume":1},"12":{"avgHighPrice":null,"highPriceVolume":0,"avgLowPrice":195751,"lowPriceVolume":2},"30":{"avgHighPrice":500,"highPriceVolume":1,"avgLowPrice":null,"lowPriceVolume":0},"39":{"avgHighPrice":4,"highPriceVolume":4000,"avgLowPrice":null,"lowPriceVolume":0},"40":{"avgHighPrice":null,"highPriceVolume":0,"avgLowPrice":4,"lowPriceVolume":40},"43":{"avgHighPrice":null,"highPriceVolume":0,"avgLowPrice":100,"lowPriceVolume":2385},"44":{"avgHighPrice":null,"highPriceVolume":0,"avgLowPrice":262,"lowPriceVolume":80},"50":{"avgHighPrice":null,"highPriceVolume":0,"avgLowPrice":16,"lowPriceVolume":73},"52":{"avgHighPrice":1,"highPriceVolume":525,"avgLowPrice":null,"lowPriceVolume":0},"53":{"avgHighPrice":15,"highPriceVolume":50455,"avgLowPrice":null,"lowPriceVolume":0},"54":{"avgHighPrice":16,"highPriceVolume":2,"avgLowPrice":null,"lowPriceVolume":0},"58":{"avgHighPrice":null,"highPriceVolume":0,"avgLowPrice":54,"lowPriceVolume":1},"64":{"avgHighPrice":98,"highPriceVolume":1,"avgLowPrice":null,"lowPriceVolume":0},"66":{"avgHighPrice":250,"highPriceVolume":1,"avgLowPrice":null,"lowPriceVolume":0},"70":{"avgHighPrice":null,"highPriceVolume":0,"avgLowPrice":955,"lowPriceVolume":21135},"91":{"avgHighPrice":370,"highPriceVolume":111,"avgLowPrice":null,"lowPriceVolume":0},"93":{"avgHighPrice":null,"highPriceVolume":0,"avgLowPrice":258,"lowPriceVolume":1},"95":{"avgHighPrice":389,"highPriceVolume":2,"avgLowPrice":null,"lowPriceVolume":0},"97":{"avgHighPrice":682,"highPriceVolume":685,"avgLowPrice":619,"lowPriceVolume":200},"99":{"avgHighPrice":5907,"highPriceVolume":3054,"avgLowPrice":null,"lowPriceVolume":0},"101":{"avgHighPrice":2187,"highPriceVolume":100,"avgLowPrice":2150,"lowPriceVolume":75},"105":{"avgHighPrice":3019,"highPriceVolume":1570,"avgLowPrice":null,"lowPriceVolume":0},"107":{"avgHighPrice":3650,"highPriceVolume":9640,"avgLowPrice":null,"lowPriceVolume":0},"111":{"avgHighPrice":3969,"highPriceVolume":10,"avgLowPrice":null,"lowPriceVolume":0},"113":{"avgHighPrice":89,"highPriceVolume":41,"avgLowPrice":null,"lowPriceVolume":0},"117":{"avgHighPrice":null,"highPriceVolume":0,"avgLowPrice":44,"lowPriceVolume":1},"121":{"avgHighPrice":5,"highPriceVolume":304,"avgLowPrice":5,"lowPriceVolume":72},"141":{"avgHighPrice":4079,"highPriceVolume":1,"avgLowPrice":4079,"lowPriceVolume":5},"143":{"avgHighPrice":null,"highPriceVolume":0,"avgLowPrice":2078,"lowPriceVolume":1},"161":{"avgHighPrice":null,"highPriceVolume":0,"avgLowPrice":850,"lowPriceVolume":141},"163":{"avgHighPrice":null,"highPriceVolume":0,"avgLowPrice":2747,"lowPriceVolume":516},"167":{"avgHighPrice":null,"highPriceVolume":0,"avgLowPrice":851,"lowPriceVolume":1},"169":{"avgHighPrice":1855,"highPriceVolume":472,"avgLowPrice":1855,"lowPriceVolume":2307},"171":{"avgHighPrice":null,"highPriceVolume":0,"avgLowPrice":1208,"lowPriceVolume":105},"199":{"avgHighPrice":null,"highPriceVolume":0,"avgLowPrice":202,"lowPriceVolume":99},"201":{"avgHighPrice":166,"highPriceVolume":45,"avgLowPrice":166,"lowPriceVolume":56},"203":{"avgHighPrice":null,"highPriceVolume":0,"avgLowPrice":185,"lowPriceVolume":4},"205":{"avgHighPrice":null,"highPriceVolume":0,"avgLowPrice":383,"lowPriceVolume":960},"207":{"avgHighPrice":5361,"highPriceVolume":168,"avgLowPrice":5306,"lowPriceVolume":604},"209":{"avgHighPrice":null,"highPriceVolume":0,"avgLowPrice":1685,"lowPriceVolume":5},"211":{"avgHighPrice":null,"highPriceVolume":0,"avgLowPrice":1855,"lowPriceVolume":2427},"213":{"avgHighPrice":null,"highPriceVolume":0,"avgLowPrice":2567,"lowPriceVolume":956},"215":{"avgHighPrice":2841,"highPriceVolume":78,"avgLowPrice":2841,"lowPriceVolume":474},"217":{"avgHighPrice":null,"highPriceVolume":0,"avgLowPrice":1965,"lowPriceVolume":1262},"219":{"avgHighPrice":null,"highPriceVolume":0,"avgLowPrice":3583,"lowPriceVolume":74},"221":{"avgHighPrice":3,"highPriceVolume":1423,"avgLowPrice":3,"lowPriceVolume":28},"223":{"avgHighPrice":185,"highPriceVolume":4910,"avgLowPrice":182,"lowPriceVolume":3567},"225":{"avgHighPrice":349,"highPriceVolume":90,"avgLowPrice":334,"lowPriceVolume":261},"227":{"avgHighPrice":4,"highPriceVolume":1,"avgLowPrice":4,"lowPriceVolume":1005},"229":{"avgHighPrice":null,"highPriceVolume":0,"avgLowPrice":2,"lowPriceVolume":2},"231":{"avgHighPrice":575,"highPriceVolume":2962,"avgLowPrice":null,"lowPriceVolume":0},"233":{"avgHighPrice":283,"highPriceVolume":1,"avgLowPrice":262,"lowPriceVolume":1},"235":{"avgHighPrice":506,"highPriceVolume":2,"avgLowPrice":460,"lowPriceVolume":1},"237":{"avgHighPrice":440,"highPriceVolume":2,"avgLowPrice":421,"lowPriceVolume":243},"239":{"avgHighPrice":478,"highPriceVolume":11029,"avgLowPrice":470,"lowPriceVolume":1020},"245":{"avgHighPrice":1384,"highPriceVolume":272,"avgLowPrice":1340,"lowPriceVolume":423},"247":{"avgHighPrice":332,"highPriceVolume":4,"avgLowPrice":null,"lowPriceVolume":0},"251":{"avgHighPrice":211,"highPriceVolume":262,"avgLowPrice":208,"lowPriceVolume":157},"253":{"avgHighPrice":261,"highPriceVolume":99,"avgLowPrice":251,"lowPriceVolume":90},"257":{"avgHighPrice":null,"highPriceVolume":0,"avgLowPrice":5540,"lowPriceVolume":425},"259":{"avgHighPrice":1872,"highPriceVolume":17,"avgLowPrice":1846,"lowPriceVolume":392},"261":{"avgHighPrice":2024,"highPriceVolume":1487,"avgLowPrice":1969,"lowPriceVolume":32},"263":{"avgHighPrice":2715,"highPriceVolume":2,"avgLowPrice":2700,"lowPriceVolume":277},"267":{"avgHighPrice":null,"highPriceVolume":0,"avgLowPrice":1870,"lowPriceVolume":60},"269":{"avgHighPrice":null,"highPriceVolume":0,"avgLowPrice":3700,"lowPriceVolume":234},"299":{"avgHighPrice":null,"highPriceVolume":0,"avgLowPrice":1251,"lowPriceVolume":80},"301":{"avgHighPrice":2,"highPriceVolume":1,"avgLowPrice":null,"lowPriceVolume":0},"303":{"avgHighPrice":40,"highPriceVolume":14,"avgLowPrice":null,"lowPriceVolume":0},"309":{"avgHighPrice":450,"highPriceVolume":1,"avgLowPrice":null,"lowPriceVolume":0},"313":{"avgHighPrice":5,"highPriceVolume":2,"avgLowPrice":null,"lowPriceVolume":0},"314":{"avgHighPrice":3,"highPriceVolume":166603,"avgLowPrice":2,"lowPriceVolume":30009},"321":{"avgHighPrice":null,"highPriceVolume":0,"avgLowPrice":28,"lowPriceVolume":20},"325":{"avgHighPrice":20,"highPriceVolume":2180,"avgLowPrice":null,"lowPriceVolume":0},"327":{"avgHighPrice":null,"highPriceVolume":0,"avgLowPrice":35,"lowPriceVolume":41},"329":{"avgHighPrice":52,"highPriceVolume":22,"avgLowPrice":52,"lowPriceVolume":28},"331":{"avgHighPrice":47,"highPriceVolume":335,"avgLowPrice":46,"lowPriceVolume":329},"333":{"avgHighPrice":32,"highPriceVolume":11,"avgLowPrice":29,"lowPriceVolume":31},"335":{"avgHighPrice":null,"highPriceVolume":0,"avgLowPrice":38,"lowPriceVolume":306},"347":{"avgHighPrice":57,"highPriceVolume":93,"avgLowPrice":50,"lowPriceVolume":2285},"349":{"avgHighPrice":null,"highPriceVolume":0,"avgLowPrice":127,"lowPriceVolume":48},"353":{"avgHighPrice":36,"highPriceVolume":10,"avgLowPrice":null,"lowPriceVolume":0},"355":{"avgHighPrice":null,"highPriceVolume":0,"avgLowPrice":32,"lowPriceVolume":1},"359":{"avgHighPrice":59,"highPriceVolume":743,"avgLowPrice":null,"lowPriceVolume":0},"361":{"avgHighPrice":92,"highPriceVolume":1302,"avgLowPrice":88,"lowPriceVolume":2667},"363":{"avgHighPrice":14,"highPriceVolume":277,"avgLowPrice":14,"lowPriceVolume":10000},"365":{"avgHighPrice":74,"highPriceVolume":140,"avgLowPrice":null,"lowPriceVolume":0},"371":{"avgHighPrice":215,"highPriceVolume":76,"avgLowPrice":210,"lowPriceVolume":351},"373":{"avgHighPrice":205,"highPriceVolume":64,"avgLowPrice":null,"lowPriceVolume":0},"377":{"avgHighPrice":151,"highPriceVolume":453,"avgLowPrice":150,"lowPriceVolume":6},"379":{"avgHighPrice":140,"highPriceVolume":298,"avgLowPrice":136,"lowPriceVolume":528},"383":{"avgHighPrice":612,"highPriceVolume":436,"avgLowPrice":612,"lowPriceVolume":528},"385":{"avgHighPrice":806,"highPriceVolume":11031,"avgLowPrice":799,"lowPriceVolume":2208},"389":{"avgHighPrice":null,"highPriceVolume":0,"avgLowPrice":1207,"lowPriceVolume":82},"391":{"avgHighPrice":1573,"highPriceVolume":640,"avgLowPrice":1526,"lowPriceVolume":156},"397":{"avgHighPrice":null,"highPriceVolume":0,"avgLowPrice":889,"lowPriceVolume":3},"401":{"avgHighPrice":5,"highPriceVolume":250,"avgLowPrice":null,"lowPriceVolume":0},"407":{"avgHighPrice":null,"highPriceVolume":0,"avgLowPrice":30,"lowPriceVolume":1},"411":{"avgHighPrice":25,"highPriceVolume":1,"avgLowPrice":null,"lowPriceVolume":0},"434":{"avgHighPrice":67,"highPriceVolume":6,"avgLowPrice":null,"lowPriceVolume":0},"436":{"avgHighPrice":15,"highPriceVolume":4,"avgLowPrice":15,"lowPriceVolume":160},"440":{"avgHighPrice":78,"highPriceVolume":4780,"avgLowPrice":77,"lowPriceVolume":847},"442":{"avgHighPrice":null,"highPriceVolume":0,"avgLowPrice":61,"lowPriceVolume":7686},"444":{"avgHighPrice":145,"highPriceVolume":30835,"avgLowPrice":144,"lowPriceVolume":1571},"447":{"avgHighPrice":null,"highPriceVolume":0,"avgLowPrice":148,"lowPriceVolume":9836},"449":{"avgHighPrice":656,"highPriceVolume":4865,"avgLowPrice":639,"lowPriceVolume":4743},"451":{"avgHighPrice":10592,"highPriceVolume":376,"avgLowPrice":10544,"lowPriceVolume":8076},"453":{"avgHighPrice":199,"highPriceVolume":60832,"avgLowPrice":195,"lowPriceVolume":9872},"464":{"avgHighPrice":null,"highPriceVolume":0,"avgLowPrice":390,"lowPriceVolume":1},"526":{"avgHighPrice":28,"highPriceVolume":449,"avgLowPrice":null,"lowPriceVolume":0},"530":{"avgHighPrice":315,"highPriceVolume":2,"avgLowPrice":null,"lowPriceVolume":0},"534":{"avgHighPrice":null,"highPriceVolume":0,"avgLowPrice":720,"lowPriceVolume":218},"536":{"avgHighPrice":2620,"highPriceVolume":196,"avgLowPrice":2569,"lowPriceVolume":1135},"542":{"avgHighPrice":75,"highPriceVolume":1,"avgLowPrice":null,"lowPriceVolume":0},"554":{"avgHighPrice":4,"highPriceVolume":662278,"avgLowPrice":null,"lowPriceVolume":0},"555":{"avgHighPrice":4,"highPriceVolume":468197,"avgLowPrice":5,"lowPriceVolume":218},"556":{"avgHighPrice":4,"highPriceVolume":826672,"avgLowPrice":6,"lowPriceVolume":24400},"557":{"avgHighPrice":4,"highPriceVolume":609916,"avgLowPrice":5,"lowPriceVolume":100228},"558":{"avgHighPrice":4,"highPriceVolume":100,"avgLowPrice":null,"lowPriceVolume":0},"559":{"avgHighPrice":5,"highPriceVolume":1006,"avgLowPrice":null,"lowPriceVolume":0},"560":{"avgHighPrice":191,"highPriceVolume":75330,"avgLowPrice":189,"lowPriceVolume":92520},"561":{"avgHighPrice":117,"highPriceVolume":33491,"avgLowPrice":116,"lowPriceVolume":53605},"562":{"avgHighPrice":108,"highPriceVolume":34175,"avgLowPrice":104,"lowPriceVolume":173056},"563":{"avgHighPrice":125,"highPriceVolume":3591,"avgLowPrice":123,"lowPriceVolume":33660},"564":{"avgHighPrice":94,"highPriceVolume":3801,"avgLowPrice":92,"lowPriceVolume":33266},"565":{"avgHighPrice":287,"highPriceVolume":80018,"avgLowPrice":283,"lowPriceVolume":199199},"566":{"avgHighPrice":381,"highPriceVolume":57400,"avgLowPrice":364,"lowPriceVolume":265619},"567":{"avgHighPrice":null,"highPriceVolume":0,"avgLowPrice":55,"lowPriceVolume":275},"569":{"avgHighPrice":2190,"highPriceVolume":1000,"avgLowPrice":null,"lowPriceVolume":0},"571":{"avgHighPrice":1805,"highPriceVolume":952,"avgLowPrice":1803,"lowPriceVolume":135},"573":{"avgHighPrice":null,"highPriceVolume":0,"avgLowPrice":2260,"lowPriceVolume":682},"575":{"avgHighPrice":null,"highPriceVolume":0,"avgLowPrice":1905,"lowPriceVolume":1935},"577":{"avgHighPrice":null,"highPriceVolume":0,"avgLowPrice":774,"lowPriceVolume":2},"579":{"avgHighPrice":195,"highPriceVolume":1,"avgLowPrice":null,"lowPriceVolume":0},"590":{"avgHighPrice":103,"highPriceVolume":4,"avgLowPrice":null,"lowPriceVolume":0},"592":{"avgHighPrice":46,"highPriceVolume":2,"avgLowPrice":45,"lowPriceVolume":2},"644":{"avgHighPrice":2000,"highPriceVolume":1,"avgLowPrice":null,"lowPriceVolume":0},"658":{"avgHighPrice":2000,"highPriceVolume":1,"avgLowPrice":null,"lowPriceVolume":0},"753":{"avgHighPrice":147,"highPriceVolume":8,"avgLowPrice":null,"lowPriceVolume":0},"805":{"avgHighPrice":204,"highPriceVolume":4,"avgLowPrice":220,"lowPriceVolume":140},"806":{"avgHighPrice":17,"highPriceVolume":994,"avgLowPrice":null,"lowPriceVolume":0},"807":{"avgHighPrice":5,"highPriceVolume":12800,"avgLowPrice":4,"lowPriceVolume":6353},"808":{"avgHighPrice":null,"highPriceVolume":0,"avgLowPrice":4,"lowPriceVolume":10000},"810":{"avgHighPrice":29,"highPriceVolume":9001,"avgLowPrice":27,"lowPriceVolume":5000},"811":{"avgHighPrice":null,"highPriceVolume":0,"avgLowPrice":189,"lowPriceVolume":1875},"820":{"avgHighPrice":54,"highPriceVolume":5000,"avgLowPrice":43,"lowPriceVolume":680},"821":{"avgHighPrice":85,"highPriceVolume":5000,"avgLowPrice":null,"lowPriceVolume":0},"824":{"avgHighPrice":null,"highPriceVolume":0,"avgLowPrice":1052,"lowPriceVolume":1872},"830":{"avgHighPrice":null,"highPriceVolume":0,"avgLowPrice":200,"lowPriceVolume":55},"839":{"avgHighPrice":23,"highPriceVolume":75,"avgLowPrice":null,"lowPriceVolume":0},"849":{"avgHighPrice":92,"highPriceVolume":3,"avgLowPrice":null,"lowPriceVolume":0},"851":{"avgHighPrice":313,"highPriceVolume":4,"avgLowPrice":null,"lowPriceVolume":0},"853":{"avgHighPrice":202,"highPriceVolume":1,"avgLowPrice":198,"lowPriceVolume":12},"855":{"avgHighPrice":539,"highPriceVolume":1001,"avgLowPrice":null,"lowPriceVolume":0},"859":{"avgHighPrice":1249,"highPriceVolume":3300,"avgLowPrice":1221,"lowPriceVolume":1001},"861":{"avgHighPrice":832,"highPriceVolume":3,"avgLowPrice":830,"lowPriceVolume":34},"868":{"avgHighPrice":194,"highPriceVolume":454,"avgLowPrice":180,"lowPriceVolume":716},"882":{"avgHighPrice":4,"highPriceVolume":3000,"avgLowPrice":4,"lowPriceVolume":600},"884":{"avgHighPrice":8,"highPriceVolume":10954,"avgLowPrice":null,"lowPriceVolume":0},"886":{"avgHighPrice":10,"highPriceVolume":246,"avgLowPrice":9,"lowPriceVolume":876},"888":{"avgHighPrice":9,"highPriceVolume":1167,"avgLowPrice":9,"lowPriceVolume":13000},"890":{"avgHighPrice":44,"highPriceVolume":1031,"avgLowPrice":44,"lowPriceVolume":209},"892":{"avgHighPrice":77,"highPriceVolume":18693,"avgLowPrice":76,"lowPriceVolume":10734},"946":{"avgHighPrice":35,"highPriceVolume":3,"avgLowPrice":null,"lowPriceVolume":0},"950":{"avgHighPrice":29,"highPriceVolume":10,"avgLowPrice":null,"lowPriceVolume":0},"954":{"avgHighPrice":40,"highPriceVolume":45,"avgLowPrice":null,"lowPriceVolume":0},"960":{"avgHighPrice":154,"highPriceVolume":10,"avgLowPrice":151,"lowPriceVolume":763},"970":{"avgHighPrice":76,"highPriceVolume":1,"avgLowPrice":null,"lowPriceVolume":0},"973":{"avgHighPrice":165,"highPriceVolume":3,"avgLowPrice":null,"lowPriceVolume":0},"983":{"avgHighPrice":385,"highPriceVolume":1,"avgLowPrice":null,"lowPriceVolume":0},"985":{"avgHighPrice":null,"highPriceVolume":0,"avgLowPrice":10445,"lowPriceVolume":17},"987":{"avgHighPrice":10350,"highPriceVolume":2,"avgLowPrice":10315,"lowPriceVolume":43},"989":{"avgHighPrice":null,"highPriceVolume":0,"avgLowPrice":22328,"lowPriceVolume":2},"1007":{"avgHighPrice":81,"highPriceVolume":12,"avgLowPrice":null,"lowPriceVolume":0},"1011":{"avgHighPrice":87,"highPriceVolume":1,"avgLowPrice":null,"lowPriceVolume":0},"1013":{"avgHighPrice":175,"highPriceVolume":3,"avgLowPrice":null,"lowPriceVolume":0},"1027":{"avgHighPrice":1188,"highPriceVolume":1,"avgLowPrice":null,"lowPriceVolume":0},"1035":{"avgHighPrice":1433,"highPriceVolume":1,"avgLowPrice":833,"lowPriceVolume":1},"1044":{"avgHighPrice":null,"highPriceVolume":0,"avgLowPrice":15000,"lowPriceVolume":4},"1048":{"avgHighPrice":null,"highPriceVolume":0,"avgLowPrice":21439,"lowPriceVolume":2},"1059":{"avgHighPrice":15,"highPriceVolume":1,"avgLowPrice":null,"lowPriceVolume":0},"1061":{"avgHighPrice":32,"highPriceVolume":126,"avgLowPrice":null,"lowPriceVolume":0},"1063":{"avgHighPrice":58,"highPriceVolume":3,"avgLowPrice":null,"lowPriceVolume":0},"1065":{"avgHighPrice":1600,"highPriceVolume":1,"avgLowPrice":null,"lowPriceVolume":0},"1067":{"avgHighPrice":181,"highPriceVolume":7,"avgLowPrice":null,"lowPriceVolume":0},"1069":{"avgHighPrice":411,"highPriceVolume":1,"avgLowPrice":null,"lowPriceVolume":0},"1071":{"avgHighPrice":1474,"highPriceVolume":1,"avgLowPrice":null,"lowPriceVolume":0},"1073":{"avgHighPrice":3785,"highPriceVolume":1,"avgLowPrice":3550,"lowPriceVolume":17},"1079":{"avgHighPrice":37950,"highPriceVolume":21,"avgLowPrice":37950,"lowPriceVolume":172},"1085":{"avgHighPrice":1248,"highPriceVolume":28,"avgLowPrice":null,"lowPriceVolume":0},"1093":{"avgHighPrice":null,"highPriceVolume":0,"avgLowPrice":37968,"lowPriceVolume":22},"1095":{"avgHighPrice":6,"highPriceVolume":8,"avgLowPrice":null,"lowPriceVolume":0},"1099":{"avgHighPrice":2309,"highPriceVolume":1,"avgLowPrice":null,"lowPriceVolume":0},"1101":{"avgHighPrice":129,"highPriceVolume":1,"avgLowPrice":82,"lowPriceVolume":1},"1105":{"avgHighPrice":500,"highPriceVolume":2,"avgLowPrice":null,"lowPriceVolume":0},"1113":{"avgHighPrice":29930,"highPriceVolume":2,"avgLowPrice":29560,"lowPriceVolume":5},"1115":{"avgHighPrice":93,"highPriceVolume":2,"avgLowPrice":null,"lowPriceVolume":0},"1119":{"avgHighPrice":1000,"highPriceVolume":100,"avgLowPrice":null,"lowPriceVolume":0},"1123":{"avgHighPrice":9580,"highPriceVolume":116,"avgLowPrice":9570,"lowPriceVolume":4},"1127":{"avgHighPrice":38701,"highPriceVolume":27,"avgLowPrice":38524,"lowPriceVolume":67},"1131":{"avgHighPrice":null,"highPriceVolume":0,"avgLowPrice":25,"lowPriceVolume":1},"1133":{"avgHighPrice":352,"highPriceVolume":2,"avgLowPrice":null,"lowPriceVolume":0},"1139":{"avgHighPrice":30,"highPriceVolume":1,"avgLowPrice":17,"lowPriceVolume":2},"1141":{"avgHighPrice":69,"highPriceVolume":3,"avgLowPrice":null,"lowPriceVolume":0},"1145":{"avgHighPrice":null,"highPriceVolume":0,"avgLowPrice":861,"lowPriceVolume":1},"1147":{"avgHighPrice":11360,"highPriceVolume":72,"avgLowPrice":11129,"lowPriceVolume":3},"1149":{"avgHighPrice":58832,"highPriceVolume":1,"avgLowPrice":58869,"lowPriceVolume":20},"1155":{"avgHighPrice":95,"highPriceVolume":1,"avgLowPrice":null,"lowPriceVolume":0},"1159":{"avgHighPrice":null,"highPriceVolume":0,"avgLowPrice":716,"lowPriceVolume":5},"1161":{"avgHighPrice":null,"highPriceVolume":0,"avgLowPrice":1866,"lowPriceVolume":51},"1163":{"avgHighPrice":20681,"highPriceVolume":88,"avgLowPrice":20685,"lowPriceVolume":79},"1169":{"avgHighPrice":24,"highPriceVolume":1,"avgLowPrice":null,"lowPriceVolume":0},"1179":{"avgHighPrice":471,"highPriceVolume":2,"avgLowPrice":null,"lowPriceVolume":0},"1185":{"avgHighPrice":null,"highPriceVolume":0,"avgLowPrice":22726,"lowPriceVolume":1},"1189":{"avgHighPrice":167,"highPriceVolume":2,"avgLowPrice":null,"lowPriceVolume":0},"1191":{"avgHighPrice":78,"highPriceVolume":6,"avgLowPrice":null,"lowPriceVolume":0},"1193":{"avgHighPrice":275,"highPriceVolume":127,"avgLowPrice":260,"lowPriceVolume":1},"1197":{"avgHighPrice":null,"highPriceVolume":0,"avgLowPrice":1022,"lowPriceVolume":1},"1199":{"avgHighPrice":3021,"highPriceVolume":1,"avgLowPrice":null,"lowPriceVolume":0},"1201":{"avgHighPrice":null,"highPriceVolume":0,"avgLowPrice":32122,"lowPriceVolume":167},"1203":{"avgHighPrice":13,"highPriceVolume":1,"avgLowPrice":10,"lowPriceVolume":2},"1211":{"avgHighPrice":null,"highPriceVolume":0,"avgLowPrice":281,"lowPriceVolume":1},"1213":{"avgHighPrice":null,"highPriceVolume":0,"avgLowPrice":4651,"lowPriceVolume":2},"1215":{"avgHighPrice":null,"highPriceVolume":0,"avgLowPrice":17300,"lowPriceVolume":45},"1237":{"avgHighPrice":null,"highPriceVolume":0,"avgLowPrice":389,"lowPriceVolume":3},"1239":{"avgHighPrice":348,"highPriceVolume":1,"avgLowPrice":null,"lowPriceVolume":0},"1247":{"avgHighPrice":null,"highPriceVolume":0,"avgLowPrice":11888,"lowPriceVolume":1},"1249":{"avgHighPrice":null,"highPriceVolume":0,"avgLowPrice":40239,"lowPriceVolume":1},"1265":{"avgHighPrice":68,"highPriceVolume":2,"avgLowPrice":null,"lowPriceVolume":0},"1267":{"avgHighPrice":194,"highPriceVolume":1,"avgLowPrice":null,"lowPriceVolume":0},"1271":{"avgHighPrice":1724,"highPriceVolume":2,"avgLowPrice":1691,"lowPriceVolume":1},"1273":{"avgHighPrice":367,"highPriceVolume":1,"avgLowPrice":359,"lowPriceVolume":2},"1275":{"avgHighPrice":19432,"highPriceVolume":2,"avgLowPrice":18768,"lowPriceVolume":39},"1281":{"avgHighPrice":76,"highPriceVolume":2,"avgLowPrice":null,"lowPriceVolume":0},"1285":{"avgHighPrice":292,"highPriceVolume":1,"avgLowPrice":null,"lowPriceVolume":0},"1289":{"avgHighPrice":12390,"highPriceVolume":2,"avgLowPrice":12099,"lowPriceVolume":1},"1295":{"avgHighPrice":104,"highPriceVolume":2,"avgLowPrice":100,"lowPriceVolume":1},"1301":{"avgHighPrice":null,"highPriceVolume":0,"avgLowPrice":1650,"lowPriceVolume":5},"1303":{"avgHighPrice":18759,"highPriceVolume":12,"avgLowPrice":18775,"lowPriceVolume":70},"1305":{"avgHighPrice":59254,"highPriceVolume":2,"avgLowPrice":59254,"lowPriceVolume":17},"1309":{"avgHighPrice":33,"highPriceVolume":125,"avgLowPrice":null,"lowPriceVolume":0},"1311":{"avgHighPrice":321,"highPriceVolume":6,"avgLowPrice":321,"lowPriceVolume":13},"1315":{"avgHighPrice":null,"highPriceVolume":0,"avgLowPrice":1235,"lowPriceVolume":1},"1319":{"avgHighPrice":null,"highPriceVolume":0,"avgLowPrice":38100,"lowPriceVolume":5},"1325":{"avgHighPrice":null,"highPriceVolume":0,"avgLowPrice":120,"lowPriceVolume":1},"1329":{"avgHighPrice":null,"highPriceVolume":0,"avgLowPrice":500,"lowPriceVolume":1},"1331":{"avgHighPrice":1460,"highPriceVolume":1,"avgLowPrice":1460,"lowPriceVolume":10},"1333":{"avgHighPrice":15755,"highPriceVolume":29,"avgLowPrice":15006,"lowPriceVolume":47},"1339":{"avgHighPrice":148,"highPriceVolume":1,"avgLowPrice":null,"lowPriceVolume":0},"1347":{"avgHighPrice":null,"highPriceVolume":0,"avgLowPrice":24901,"lowPriceVolume":49},"1351":{"avgHighPrice":179,"highPriceVolume":20,"avgLowPrice":150,"lowPriceVolume":12},"1353":{"avgHighPrice":151,"highPriceVolume":6,"avgLowPrice":null,"lowPriceVolume":0},"1355":{"avgHighPrice":276,"highPriceVolume":11,"avgLowPrice":null,"lowPriceVolume":0},"1357":{"avgHighPrice":793,"highPriceVolume":1,"avgLowPrice":null,"lowPriceVolume":0},"1359":{"avgHighPrice":null,"highPriceVolume":0,"avgLowPrice":7381,"lowPriceVolume":10},"1361":{"avgHighPrice":772,"highPriceVolume":1,"avgLowPrice":null,"lowPriceVolume":0},"1365":{"avgHighPrice":null,"highPriceVolume":0,"avgLowPrice":160,"lowPriceVolume":1},"1369":{"avgHighPrice":null,"highPriceVolume":0,"avgLowPrice":1000,"lowPriceVolume":1},"1371":{"avgHighPrice":null,"highPriceVolume":0,"avgLowPrice":2259,"lowPriceVolume":4},"1373":{"avgHighPrice":null,"highPriceVolume":0,"avgLowPrice":24660,"lowPriceVolume":3},"1377":{"avgHighPrice":119536,"highPriceVolume":1,"avgLowPrice":119393,"lowPriceVolume":34},"1381":{"avgHighPrice":1795,"highPriceVolume":2,"avgLowPrice":1702,"lowPriceVolume":6},"1383":{"avgHighPrice":1518,"highPriceVolume":3,"avgLowPrice":null,"lowPriceVolume":0},"1385":{"avgHighPrice":899,"highPriceVolume":1,"avgLowPrice":740,"lowPriceVolume":1},"1387":{"avgHighPrice":1395,"highPriceVolume":5,"avgLowPrice":null,"lowPriceVolume":0},"1389":{"avgHighPrice":311,"highPriceVolume":1,"avgLowPrice":300,"lowPriceVolume":2},"1391":{"avgHighPrice":7337,"highPriceVolume":475,"avgLowPrice":7312,"lowPriceVolume":1027},"1393":{"avgHighPrice":null,"highPriceVolume":0,"avgLowPrice":9050,"lowPriceVolume":26},"1395":{"avgHighPrice":null,"highPriceVolume":0,"avgLowPrice":8909,"lowPriceVolume":3505},"1397":{"avgHighPrice":8953,"highPriceVolume":1,"avgLowPrice":8953,"lowPriceVolume":391},"1399":{"avgHighPrice":null,"highPriceVolume":0,"avgLowPrice":8851,"lowPriceVolume":6},"1401":{"avgHighPrice":null,"highPriceVolume":0,"avgLowPrice":25006,"lowPriceVolume":42},"1403":{"avgHighPrice":null,"highPriceVolume":0,"avgLowPrice":25018,"lowPriceVolume":62},"1405":{"avgHighPrice":null,"highPriceVolume":0,"avgLowPrice":25175,"lowPriceVolume":25},"1407":{"avgHighPrice":null,"highPriceVolume":0,"avgLowPrice":25054,"lowPriceVolume":16},"1424":{"avgHighPrice":23,"highPriceVolume":2,"avgLowPrice":null,"lowPriceVolume":0},"1426":{"avgHighPrice":null,"highPriceVolume":0,"avgLowPrice":900,"lowPriceVolume":1},"1432":{"avgHighPrice":null,"highPriceVolume":0,"avgLowPrice":8274,"lowPriceVolume":9},"1434":{"avgHighPrice":null,"highPriceVolume":0,"avgLowPrice":29250,"lowPriceVolume":1},"1436":{"avgHighPrice":12,"highPriceVolume":1,"avgLowPrice":12,"lowPriceVolume":50},"1440":{"avgHighPrice":null,"highPriceVolume":0,"avgLowPrice":525,"lowPriceVolume":113},"1446":{"avgHighPrice":null,"highPriceVolume":0,"avgLowPrice":1921,"lowPriceVolume":2},"1448":{"avgHighPrice":null,"highPriceVolume":0,"avgLowPrice":1351,"lowPriceVolume":38},"1452":{"avgHighPrice":169,"highPriceVolume":1,"avgLowPrice":null,"lowPriceVolume":0},"1454":{"avgHighPrice":247,"highPriceVolume":2,"avgLowPrice":null,"lowPriceVolume":0},"1474":{"avgHighPrice":null,"highPriceVolume":0,"avgLowPrice":1127,"lowPriceVolume":1},"1476":{"avgHighPrice":null,"highPriceVolume":0,"avgLowPrice":2987,"lowPriceVolume":1},"1511":{"avgHighPrice":22,"highPriceVolume":12,"avgLowPrice":24,"lowPriceVolume":498},"1513":{"avgHighPrice":908,"highPriceVolume":31001,"avgLowPrice":907,"lowPriceVolume":1630},"1515":{"avgHighPrice":116,"highPriceVolume":1829,"avgLowPrice":113,"lowPriceVolume":1764},"1517":{"avgHighPrice":12,"highPriceVolume":3,"avgLowPrice":null,"lowPriceVolume":0},"1519":{"avgHighPrice":21,"highPriceVolume":221,"avgLowPrice":null,"lowPriceVolume":0},"1521":{"avgHighPrice":34,"highPriceVolume":1543,"avgLowPrice":null,"lowPriceVolume":0},"1539":{"avgHighPrice":28,"highPriceVolume":207,"avgLowPrice":28,"lowPriceVolume":100},"1540":{"avgHighPrice":130,"highPriceVolume":1,"avgLowPrice":null,"lowPriceVolume":0},"1573":{"avgHighPrice":267,"highPriceVolume":1,"avgLowPrice":null,"lowPriceVolume":0},"1592":{"avgHighPrice":75,"highPriceVolume":2,"avgLowPrice":null,"lowPriceVolume":0},"1601":{"avgHighPrice":1872,"highPriceVolume":99,"avgLowPrice":1857,"lowPriceVolume":373},"1603":{"avgHighPrice":null,"highPriceVolume":0,"avgLowPrice":962,"lowPriceVolume":233},"1605":{"avgHighPrice":538,"highPriceVolume":7838,"avgLowPrice":525,"lowPriceVolume":31},"1607":{"avgHighPrice":331,"highPriceVolume":2,"avgLowPrice":321,"lowPriceVolume":263},"1609":{"avgHighPrice":135,"highPriceVolume":1,"avgLowPrice":134,"lowPriceVolume":559},"1615":{"avgHighPrice":null,"highPriceVolume":0,"avgLowPrice":11127,"lowPriceVolume":257},"1617":{"avgHighPrice":null,"highPriceVolume":0,"avgLowPrice":3367,"lowPriceVolume":1177},"1619":{"avgHighPrice":1341,"highPriceVolume":1372,"avgLowPrice":1324,"lowPriceVolume":370},"1621":{"avgHighPrice":643,"highPriceVolume":50,"avgLowPrice":643,"lowPriceVolume":2438},"1623":{"avgHighPrice":323,"highPriceVolume":367,"avgLowPrice":323,"lowPriceVolume":3522},"1625":{"avgHighPrice":71,"highPriceVolume":100,"avgLowPrice":null,"lowPriceVolume":0},"1629":{"avgHighPrice":null,"highPriceVolume":0,"avgLowPrice":2265,"lowPriceVolume":6},"1631":{"avgHighPrice":null,"highPriceVolume":0,"avgLowPrice":16653,"lowPriceVolume":35},"1635":{"avgHighPrice":151,"highPriceVolume":1,"avgLowPrice":147,"lowPriceVolume":4},"1637":{"avgHighPrice":null,"highPriceVolume":0,"avgLowPrice":463,"lowPriceVolume":1},"1639":{"avgHighPrice":null,"highPriceVolume":0,"avgLowPrice":661,"lowPriceVolume":9},"1641":{"avgHighPrice":1062,"highPriceVolume":1,"avgLowPrice":1040,"lowPriceVolume":7},"1643":{"avgHighPrice":1929,"highPriceVolume":28,"avgLowPrice":1901,"lowPriceVolume":104},"1645":{"avgHighPrice":null,"highPriceVolume":0,"avgLowPrice":10262,"lowPriceVolume":1},"1654":{"avgHighPrice":148,"highPriceVolume":1,"avgLowPrice":144,"lowPriceVolume":3041},"1656":{"avgHighPrice":507,"highPriceVolume":6257,"avgLowPrice":492,"lowPriceVolume":441},"1658":{"avgHighPrice":725,"highPriceVolume":1,"avgLowPrice":715,"lowPriceVolume":1780},"1660":{"avgHighPrice":1174,"highPriceVolume":6994,"avgLowPrice":1161,"lowPriceVolume":3620},"1662":{"avgHighPrice":null,"highPriceVolume":0,"avgLowPrice":2026,"lowPriceVolume":263},"1664":{"avgHighPrice":null,"highPriceVolume":0,"avgLowPrice":11175,"lowPriceVolume":4},"1679":{"avgHighPrice":null,"highPriceVolume":0,"avgLowPrice":1102,"lowPriceVolume":52},"1681":{"avgHighPrice":null,"highPriceVolume":0,"avgLowPrice":1911,"lowPriceVolume":52},"1692":{"avgHighPrice":169,"highPriceVolume":30,"avgLowPrice":null,"lowPriceVolume":0},"1704":{"avgHighPrice":null,"highPriceVolume":0,"avgLowPrice":11500,"lowPriceVolume":170},"1712":{"avgHighPrice":11928,"highPriceVolume":1,"avgLowPrice":null,"lowPriceVolume":0},"1718":{"avgHighPrice":458,"highPriceVolume":2,"avgLowPrice":null,"lowPriceVolume":0},"1724":{"avgHighPrice":null,"highPriceVolume":0,"avgLowPrice":666,"lowPriceVolume":1},"1725":{"avgHighPrice":1355,"highPriceVolume":2,"avgLowPrice":null,"lowPriceVolume":0},"1731":{"avgHighPrice":2064,"highPriceVolume":8,"avgLowPrice":2049,"lowPriceVolume":7},"1733":{"avgHighPrice":99,"highPriceVolume":9,"avgLowPrice":99,"lowPriceVolume":1},"1734":{"avgHighPrice":7,"highPriceVolume":969,"avgLowPrice":7,"lowPriceVolume":51},"1735":{"avgHighPrice":181,"highPriceVolume":31,"avgLowPrice":null,"lowPriceVolume":0},"1737":{"avgHighPrice":9,"highPriceVolume":1,"avgLowPrice":9,"lowPriceVolume":257},"1739":{"avgHighPrice":117,"highPriceVolume":11590,"avgLowPrice":null,"lowPriceVolume":0},"1741":{"avgHighPrice":150,"highPriceVolume":704,"avgLowPrice":146,"lowPriceVolume":500},"1743":{"avgHighPrice":157,"highPriceVolume":1,"avgLowPrice":null,"lowPriceVolume":0},"1747":{"avgHighPrice":null,"highPriceVolume":0,"avgLowPrice":4107,"lowPriceVolume":1540},"1749":{"avgHighPrice":2555,"highPriceVolume":152,"avgLowPrice":2591,"lowPriceVolume":1824},"1751":{"avgHighPrice":2001,"highPriceVolume":324,"avgLowPrice":2044,"lowPriceVolume":1242},"1753":{"avgHighPrice":null,"highPriceVolume":0,"avgLowPrice":1781,"lowPriceVolume":3401},"1755":{"avgHighPrice":350,"highPriceVolume":12,"avgLowPrice":null,"lowPriceVolume":0},"1761":{"avgHighPrice":115,"highPriceVolume":26,"avgLowPrice":null,"lowPriceVolume":0},"1763":{"avgHighPrice":388,"highPriceVolume":1,"avgLowPrice":null,"lowPriceVolume":0},"1765":{"avgHighPrice":190,"highPriceVolume":1,"avgLowPrice":null,"lowPriceVolume":0},"1767":{"avgHighPrice":352,"highPriceVolume":1,"avgLowPrice":null,"lowPriceVolume":0},"1775":{"avgHighPrice":95,"highPriceVolume":4,"avgLowPrice":94,"lowPriceVolume":4379},"1777":{"avgHighPrice":99,"highPriceVolume":414,"avgLowPrice":null,"lowPriceVolume":0},"1779":{"avgHighPrice":null,"highPriceVolume":0,"avgLowPrice":3,"lowPriceVolume":13000},"1785":{"avgHighPrice":53,"highPriceVolume":1,"avgLowPrice":null,"lowPriceVolume":0},"1794":{"avgHighPrice":399,"highPriceVolume":8,"avgLowPrice":null,"lowPriceVolume":0},"1823":{"avgHighPrice":164,"highPriceVolume":100,"avgLowPrice":null,"lowPriceVolume":0},"1833":{"avgHighPrice":311,"highPriceVolume":1,"avgLowPrice":null,"lowPriceVolume":0},"1835":{"avgHighPrice":542,"highPriceVolume":1,"avgLowPrice":null,"lowPriceVolume":0},"1837":{"avgHighPrice":222,"highPriceVolume":1,"avgLowPrice":null,"lowPriceVolume":0},"1891":{"avgHighPrice":294,"highPriceVolume":682,"avgLowPrice":null,"lowPriceVolume":0},"1897":{"avgHighPrice":null,"highPriceVolume":0,"avgLowPrice":400,"lowPriceVolume":2},"1909":{"avgHighPrice":212,"highPriceVolume":3,"avgLowPrice":null,"lowPriceVolume":0},"1913":{"avgHighPrice":111,"highPriceVolume":1,"avgLowPrice":null,"lowPriceVolume":0},"1917":{"avgHighPrice":79,"highPriceVolume":5,"avgLowPrice":null,"lowPriceVolume":0},"1923":{"avgHighPrice":21,"highPriceVolume":1,"avgLowPrice":null,"lowPriceVolume":0},"1925":{"avgHighPrice":9,"highPriceVolume":10,"avgLowPrice":null,"lowPriceVolume":0},"1927":{"avgHighPrice":36,"highPriceVolume":8,"avgLowPrice":null,"lowPriceVolume":0},"1929":{"avgHighPrice":40,"highPriceVolume":1,"avgLowPrice":null,"lowPriceVolume":0},"1931":{"avgHighPrice":24,"highPriceVolume":1,"avgLowPrice":24,"lowPriceVolume":13},"1935":{"avgHighPrice":3,"highPriceVolume":22,"avgLowPrice":null,"lowPriceVolume":0},"1937":{"avgHighPrice":8,"highPriceVolume":1,"avgLowPrice":null,"lowPriceVolume":0},"1939":{"avgHighPrice":5,"highPriceVolume":2,"avgLowPrice":null,"lowPriceVolume":0},"1941":{"avgHighPrice":27,"highPriceVolume":21,"avgLowPrice":null,"lowPriceVolume":0},"1942":{"avgHighPrice":17,"highPriceVolume":2,"avgLowPrice":null,"lowPriceVolume":0},"1947":{"avgHighPrice":null,"highPriceVolume":0,"avgLowPrice":6,"lowPriceVolume":1},"1951":{"avgHighPrice":92,"highPriceVolume":1,"avgLowPrice":null,"lowPriceVolume":0},"1957":{"avgHighPrice":25,"highPriceVolume":1,"avgLowPrice":null,"lowPriceVolume":0},"1963":{"avgHighPrice":47,"highPriceVolume":15,"avgLowPrice":null,"lowPriceVolume":0},"1965":{"avgHighPrice":14,"highPriceVolume":1102,"avgLowPrice":14,"lowPriceVolume":6001},"1975":{"avgHighPrice":63,"highPriceVolume":204,"avgLowPrice":null,"lowPriceVolume":0},"1978":{"avgHighPrice":129,"highPriceVolume":2,"avgLowPrice":null,"lowPriceVolume":0},"1982":{"avgHighPrice":18,"highPriceVolume":1,"avgLowPrice":null,"lowPriceVolume":0},"1985":{"avgHighPrice":49,"highPriceVolume":8,"avgLowPrice":null,"lowPriceVolume":0},"1987":{"avgHighPrice":85,"highPriceVolume":19795,"avgLowPrice":82,"lowPriceVolume":13342},"1993":{"avgHighPrice":3,"highPriceVolume":51403,"avgLowPrice":null,"lowPriceVolume":0},"2003":{"avgHighPrice":88,"highPriceVolume":44,"avgLowPrice":null,"lowPriceVolume":0},"2007":{"avgHighPrice":93,"highPriceVolume":1,"avgLowPrice":null,"lowPriceVolume":0},"2011":{"avgHighPrice":null,"highPriceVolume":0,"avgLowPrice":320,"lowPriceVolume":1},"2015":{"avgHighPrice":130,"highPriceVolume":2,"avgLowPrice":null,"lowPriceVolume":0},"2028":{"avgHighPrice":850,"highPriceVolume":1,"avgLowPrice":null,"lowPriceVolume":0},"2084":{"avgHighPrice":2200,"highPriceVolume":7,"avgLowPrice":null,"lowPriceVolume":0},"2102":{"avgHighPrice":105,"highPriceVolume":1,"avgLowPrice":null,"lowPriceVolume":0},"2108":{"avgHighPrice":154,"highPriceVolume":2,"avgLowPrice":null,"lowPriceVolume":0},"2114":{"avgHighPrice":163,"highPriceVolume":420,"avgLowPrice":137,"lowPriceVolume":12},"2128":{"avgHighPrice":594,"highPriceVolume":1,"avgLowPrice":null,"lowPriceVolume":0},"2132":{"avgHighPrice":34,"highPriceVolume":1,"avgLowPrice":30,"lowPriceVolume":5},"2134":{"avgHighPrice":25,"highPriceVolume":2,"avgLowPrice":null,"lowPriceVolume":0},"2136":{"avgHighPrice":110,"highPriceVolume":1,"avgLowPrice":null,"lowPriceVolume":0},"2138":{"avgHighPrice":24,"highPriceVolume":3,"avgLowPrice":null,"lowPriceVolume":0},"2301":{"avgHighPrice":691,"highPriceVolume":10,"avgLowPrice":null,"lowPriceVolume":0},"2309":{"avgHighPrice":97,"highPriceVolume":11,"avgLowPrice":null,"lowPriceVolume":0},"2313":{"avgHighPrice":null,"highPriceVolume":0,"avgLowPrice":10,"lowPriceVolume":18},"2317":{"avgHighPrice":318,"highPriceVolume":224,"avgLowPrice":null,"lowPriceVolume":0},"2325":{"avgHighPrice":117,"highPriceVolume":2,"avgLowPrice":null,"lowPriceVolume":0},"2349":{"avgHighPrice":53,"highPriceVolume":100,"avgLowPrice":null,"lowPriceVolume":0},"2351":{"avgHighPrice":149,"highPriceVolume":15,"avgLowPrice":146,"lowPriceVolume":2},"2353":{"avgHighPrice":588,"highPriceVolume":7721,"avgLowPrice":588,"lowPriceVolume":183},"2355":{"avgHighPrice":93,"highPriceVolume":5,"avgLowPrice":91,"lowPriceVolume":10},"2357":{"avgHighPrice":117,"highPriceVolume":9515,"avgLowPrice":113,"lowPriceVolume":2437},"2359":{"avgHighPrice":958,"highPriceVolume":2774,"avgLowPrice":940,"lowPriceVolume":815},"2361":{"avgHighPrice":null,"highPriceVolume":0,"avgLowPrice":1895,"lowPriceVolume":1498},"2363":{"avgHighPrice":12396,"highPriceVolume":3,"avgLowPrice":12380,"lowPriceVolume":575},"2434":{"avgHighPrice":8450,"highPriceVolume":2174,"avgLowPrice":8369,"lowPriceVolume":85},"2436":{"avgHighPrice":2530,"highPriceVolume":6,"avgLowPrice":2527,"lowPriceVolume":1874},"2440":{"avgHighPrice":3725,"highPriceVolume":6,"avgLowPrice":3707,"lowPriceVolume":115},"2442":{"avgHighPrice":3844,"highPriceVolume":3,"avgLowPrice":null,"lowPriceVolume":0},"2444":{"avgHighPrice":2650,"highPriceVolume":147,"avgLowPrice":2620,"lowPriceVolume":4},"2446":{"avgHighPrice":353,"highPriceVolume":4,"avgLowPrice":337,"lowPriceVolume":1},"2448":{"avgHighPrice":1032,"highPriceVolume":2,"avgLowPrice":null,"lowPriceVolume":0},"2452":{"avgHighPrice":1103,"highPriceVolume":9,"avgLowPrice":null,"lowPriceVolume":0},"2485":{"avgHighPrice":null,"highPriceVolume":0,"avgLowPrice":1635,"lowPriceVolume":931},"2491":{"avgHighPrice":null,"highPriceVolume":0,"avgLowPrice":2076,"lowPriceVolume":8},"2495":{"avgHighPrice":3060,"highPriceVolume":1,"avgLowPrice":2701,"lowPriceVolume":4},"2497":{"avgHighPrice":3366,"highPriceVolume":2,"avgLowPrice":3181,"lowPriceVolume":13},"2499":{"avgHighPrice":null,"highPriceVolume":0,"avgLowPrice":4984,"lowPriceVolume":2},"2503":{"avgHighPrice":7426,"highPriceVolume":94,"avgLowPrice":7351,"lowPriceVolume":4},"2505":{"avgHighPrice":null,"highPriceVolume":0,"avgLowPrice":2400,"lowPriceVolume":1602},"2507":{"avgHighPrice":2830,"highPriceVolume":400,"avgLowPrice":null,"lowPriceVolume":0},"2550":{"avgHighPrice":776,"highPriceVolume":1501,"avgLowPrice":744,"lowPriceVolume":20},"2552":{"avgHighPrice":849,"highPriceVolume":4,"avgLowPrice":829,"lowPriceVolume":9},"2568":{"avgHighPrice":1068,"highPriceVolume":2,"avgLowPrice":1039,"lowPriceVolume":6},"2570":{"avgHighPrice":1854,"highPriceVolume":3,"avgLowPrice":1831,"lowPriceVolume":24},"2572":{"avgHighPrice":null,"highPriceVolume":0,"avgLowPrice":10999,"lowPriceVolume":179},"2625":{"avgHighPrice":50144,"highPriceVolume":1,"avgLowPrice":null,"lowPriceVolume":0},"2627":{"avgHighPrice":24921,"highPriceVolume":2,"avgLowPrice":null,"lowPriceVolume":0},"2641":{"avgHighPrice":null,"highPriceVolume":0,"avgLowPrice":4401,"lowPriceVolume":1},"2675":{"avgHighPrice":null,"highPriceVolume":0,"avgLowPrice":40131,"lowPriceVolume":1},"2859":{"avgHighPrice":347,"highPriceVolume":1,"avgLowPrice":325,"lowPriceVolume":2},"2864":{"avgHighPrice":72,"highPriceVolume":7000,"avgLowPrice":null,"lowPriceVolume":0},"2866":{"avgHighPrice":270,"highPriceVolume":300,"avgLowPrice":null,"lowPriceVolume":0},"2890":{"avgHighPrice":1025,"highPriceVolume":1,"avgLowPrice":null,"lowPriceVolume":0},"2961":{"avgHighPrice":128,"highPriceVolume":2,"avgLowPrice":null,"lowPriceVolume":0},"2970":{"avgHighPrice":447,"highPriceVolume":14,"avgLowPrice":419,"lowPriceVolume":26},"2972":{"avgHighPrice":4500,"highPriceVolume":5,"avgLowPrice":null,"lowPriceVolume":0},"2998":{"avgHighPrice":null,"highPriceVolume":0,"avgLowPrice":2601,"lowPriceVolume":296},"3000":{"avgHighPrice":null,"highPriceVolume":0,"avgLowPrice":8306,"lowPriceVolume":236},"3002":{"avgHighPrice":null,"highPriceVolume":0,"avgLowPrice":2854,"lowPriceVolume":16},"3004":{"avgHighPrice":8791,"highPriceVolume":49,"avgLowPrice":null,"lowPriceVolume":0},"3010":{"avgHighPrice":null,"highPriceVolume":0,"avgLowPrice":118,"lowPriceVolume":99},"3016":{"avgHighPrice":3127,"highPriceVolume":979,"avgLowPrice":null,"lowPriceVolume":0},"3024":{"avgHighPrice":10973,"highPriceVolume":420,"avgLowPrice":10669,"lowPriceVolume":24},"3026":{"avgHighPrice":7854,"highPriceVolume":1,"avgLowPrice":null,"lowPriceVolume":0},"3028":{"avgHighPrice":5142,"highPriceVolume":1,"avgLowPrice":null,"lowPriceVolume":0},"3030":{"avgHighPrice":2552,"highPriceVolume":1,"avgLowPrice":null,"lowPriceVolume":0},"3032":{"avgHighPrice":284,"highPriceVolume":3,"avgLowPrice":null,"lowPriceVolume":0},"3040":{"avgHighPrice":137,"highPriceVolume":100,"avgLowPrice":null,"lowPriceVolume":0},"3049":{"avgHighPrice":2426,"highPriceVolume":82,"avgLowPrice":2390,"lowPriceVolume":301},"3051":{"avgHighPrice":8156,"highPriceVolume":15,"avgLowPrice":8061,"lowPriceVolume":188},"3122":{"avgHighPrice":36991,"highPriceVolume":1,"avgLowPrice":null,"lowPriceVolume":0},"3125":{"avgHighPrice":665,"highPriceVolume":1,"avgLowPrice":null,"lowPriceVolume":0},"3138":{"avgHighPrice":74,"highPriceVolume":134,"avgLowPrice":76,"lowPriceVolume":315},"3142":{"avgHighPrice":325,"highPriceVolume":115,"avgLowPrice":321,"lowPriceVolume":1},"3144":{"avgHighPrice":470,"highPriceVolume":1061,"avgLowPrice":null,"lowPriceVolume":0},"3162":{"avgHighPrice":227,"highPriceVolume":1,"avgLowPrice":null,"lowPriceVolume":0},"3204":{"avgHighPrice":null,"highPriceVolume":0,"avgLowPrice":149005,"lowPriceVolume":5},"3228":{"avgHighPrice":402,"highPriceVolume":1,"avgLowPrice":null,"lowPriceVolume":0},"3363":{"avgHighPrice":732,"highPriceVolume":10,"avgLowPrice":null,"lowPriceVolume":0},"3379":{"avgHighPrice":null,"highPriceVolume":0,"avgLowPrice":64,"lowPriceVolume":1},"3391":{"avgHighPrice":null,"highPriceVolume":0,"avgLowPrice":2586,"lowPriceVolume":5},"3410":{"avgHighPrice":11,"highPriceVolume":7,"avgLowPrice":null,"lowPriceVolume":0},"3420":{"avgHighPrice":150,"highPriceVolume":19,"avgLowPrice":null,"lowPriceVolume":0},"3678":{"avgHighPrice":5933,"highPriceVolume":2,"avgLowPrice":null,"lowPriceVolume":0},"3749":{"avgHighPrice":null,"highPriceVolume":0,"avgLowPrice":35572,"lowPriceVolume":1},"3828":{"avgHighPrice":null,"highPriceVolume":0,"avgLowPrice":1469,"lowPriceVolume":1},"3831":{"avgHighPrice":null,"highPriceVolume":0,"avgLowPrice":5915,"lowPriceVolume":1},"3837":{"avgHighPrice":null,"highPriceVolume":0,"avgLowPrice":2012,"lowPriceVolume":2},"3853":{"avgHighPrice":720,"highPriceVolume":32,"avgLowPrice":null,"lowPriceVolume":0},"4087":{"avgHighPrice":null,"highPriceVolume":0,"avgLowPrice":161002,"lowPriceVolume":20},"4089":{"avgHighPrice":12141,"highPriceVolume":2,"avgLowPrice":null,"lowPriceVolume":0},"4091":{"avgHighPrice":null,"highPriceVolume":0,"avgLowPrice":71213,"lowPriceVolume":24},"4093":{"avgHighPrice":null,"highPriceVolume":0,"avgLowPrice":47050,"lowPriceVolume":22},"4095":{"avgHighPrice":null,"highPriceVolume":0,"avgLowPrice":5520,"lowPriceVolume":4},"4097":{"avgHighPrice":6142,"highPriceVolume":2,"avgLowPrice":5475,"lowPriceVolume":2},"4105":{"avgHighPrice":null,"highPriceVolume":0,"avgLowPrice":5780,"lowPriceVolume":1},"4109":{"avgHighPrice":null,"highPriceVolume":0,"avgLowPrice":8750,"lowPriceVolume":1},"4131":{"avgHighPrice":7500,"highPriceVolume":2,"avgLowPrice":7229,"lowPriceVolume":22},"4151":{"avgHighPrice":null,"highPriceVolume":0,"avgLowPrice":1217971,"lowPriceVolume":1},"4153":{"avgHighPrice":null,"highPriceVolume":0,"avgLowPrice":184062,"lowPriceVolume":1},"4156":{"avgHighPrice":6968,"highPriceVolume":4,"avgLowPrice":null,"lowPriceVolume":0},"4161":{"avgHighPrice":26,"highPriceVolume":1,"avgLowPrice":null,"lowPriceVolume":0},"4207":{"avgHighPrice":522669,"highPriceVolume":2,"avgLowPrice":null,"lowPriceVolume":0},"4310":{"avgHighPrice":1000,"highPriceVolume":3,"avgLowPrice":null,"lowPriceVolume":0},"4315":{"avgHighPrice":957,"highPriceVolume":1,"avgLowPrice":null,"lowPriceVolume":0},"4349":{"avgHighPrice":498,"highPriceVolume":1,"avgLowPrice":null,"lowPriceVolume":0},"4355":{"avgHighPrice":529,"highPriceVolume":1,"avgLowPrice":null,"lowPriceVolume":0},"4417":{"avgHighPrice":2711,"highPriceVolume":451,"avgLowPrice":null,"lowPriceVolume":0},"4522":{"avgHighPrice":4444,"highPriceVolume":1,"avgLowPrice":null,"lowPriceVolume":0},"4532":{"avgHighPrice":4057,"highPriceVolume":1,"avgLowPrice":null,"lowPriceVolume":0},"4542":{"avgHighPrice":17,"highPriceVolume":1,"avgLowPrice":null,"lowPriceVolume":0},"4548":{"avgHighPrice":1750,"highPriceVolume":1,"avgLowPrice":null,"lowPriceVolume":0},"4585":{"avgHighPrice":null,"highPriceVolume":0,"avgLowPrice":161160,"lowPriceVolume":18},"4587":{"avgHighPrice":59848,"highPriceVolume":2,"avgLowPrice":null,"lowPriceVolume":0},"4675":{"avgHighPrice":61379,"highPriceVolume":3,"avgLowPrice":59500,"lowPriceVolume":4},"4687":{"avgHighPrice":199,"highPriceVolume":2,"avgLowPrice":null,"lowPriceVolume":0},"4695":{"avgHighPrice":80,"highPriceVolume":18650,"avgLowPrice":78,"lowPriceVolume":300},"4696":{"avgHighPrice":null,"highPriceVolume":0,"avgLowPrice":8,"lowPriceVolume":6829},"4697":{"avgHighPrice":null,"highPriceVolume":0,"avgLowPrice":97,"lowPriceVolume":820},"4698":{"avgHighPrice":107,"highPriceVolume":1000,"avgLowPrice":104,"lowPriceVolume":976},"4699":{"avgHighPrice":32,"highPriceVolume":6868,"avgLowPrice":30,"lowPriceVolume":2007},"4710":{"avgHighPrice":167674,"highPriceVolume":2,"avgLowPrice":null,"lowPriceVolume":0},"4712":{"avgHighPrice":null,"highPriceVolume":0,"avgLowPrice":1971111,"lowPriceVolume":1},"4714":{"avgHighPrice":null,"highPriceVolume":0,"avgLowPrice":1599999,"lowPriceVolume":2},"4736":{"avgHighPrice":1126000,"highPriceVolume":1,"avgLowPrice":1099909,"lowPriceVolume":3},"4738":{"avgHighPrice":446263,"highPriceVolume":2,"avgLowPrice":null,"lowPriceVolume":0},"4759":{"avgHighPrice":310523,"highPriceVolume":1,"avgLowPrice":null,"lowPriceVolume":0},"4819":{"avgHighPrice":4,"highPriceVolume":332,"avgLowPrice":null,"lowPriceVolume":0},"4820":{"avgHighPrice":8,"highPriceVolume":100,"avgLowPrice":null,"lowPriceVolume":0},"4822":{"avgHighPrice":null,"highPriceVolume":0,"avgLowPrice":77,"lowPriceVolume":21225},"4823":{"avgHighPrice":130,"highPriceVolume":400,"avgLowPrice":null,"lowPriceVolume":0},"4824":{"avgHighPrice":827,"highPriceVolume":530,"avgLowPrice":null,"lowPriceVolume":0},"4827":{"avgHighPrice":1950,"highPriceVolume":1,"avgLowPrice":null,"lowPriceVolume":0},"4842":{"avgHighPrice":873,"highPriceVolume":6,"avgLowPrice":null,"lowPriceVolume":0},"4998":{"avgHighPrice":null,"highPriceVolume":0,"avgLowPrice":239622,"lowPriceVolume":2},"5001":{"avgHighPrice":54,"highPriceVolume":1,"avgLowPrice":null,"lowPriceVolume":0},"5016":{"avgHighPrice":422,"highPriceVolume":1,"avgLowPrice":null,"lowPriceVolume":0},"5075":{"avgHighPrice":null,"highPriceVolume":0,"avgLowPrice":4871,"lowPriceVolume":294},"5099":{"avgHighPrice":5,"highPriceVolume":59,"avgLowPrice":null,"lowPriceVolume":0},"5100":{"avgHighPrice":16,"highPriceVolume":2,"avgLowPrice":null,"lowPriceVolume":0},"5104":{"avgHighPrice":null,"highPriceVolume":0,"avgLowPrice":6,"lowPriceVolume":2},"5105":{"avgHighPrice":null,"highPriceVolume":0,"avgLowPrice":15,"lowPriceVolume":1},"5106":{"avgHighPrice":null,"highPriceVolume":0,"avgLowPrice":20,"lowPriceVolume":2},"5280":{"avgHighPrice":null,"highPriceVolume":0,"avgLowPrice":72,"lowPriceVolume":2},"5281":{"avgHighPrice":null,"highPriceVolume":0,"avgLowPrice":119,"lowPriceVolume":12},"5283":{"avgHighPrice":null,"highPriceVolume":0,"avgLowPrice":14,"lowPriceVolume":2},"5284":{"avgHighPrice":null,"highPriceVolume":0,"avgLowPrice":56,"lowPriceVolume":1},"5285":{"avgHighPrice":null,"highPriceVolume":0,"avgLowPrice":35,"lowPriceVolume":1},"5287":{"avgHighPrice":null,"highPriceVolume":0,"avgLowPrice":75,"lowPriceVolume":2},"5288":{"avgHighPrice":null,"highPriceVolume":0,"avgLowPrice":1734,"lowPriceVolume":10},"5289":{"avgHighPrice":null,"highPriceVolume":0,"avgLowPrice":22528,"lowPriceVolume":13},"5293":{"avgHighPrice":10,"highPriceVolume":2,"avgLowPrice":10,"lowPriceVolume":29},"5294":{"avgHighPrice":17,"highPriceVolume":17,"avgLowPrice":17,"lowPriceVolume":1},"5295":{"avgHighPrice":28057,"highPriceVolume":159,"avgLowPrice":27394,"lowPriceVolume":365},"5296":{"avgHighPrice":973,"highPriceVolume":68,"avgLowPrice":906,"lowPriceVolume":13},"5297":{"avgHighPrice":null,"highPriceVolume":0,"avgLowPrice":112,"lowPriceVolume":20},"5298":{"avgHighPrice":null,"highPriceVolume":0,"avgLowPrice":402,"lowPriceVolume":19},"5299":{"avgHighPrice":null,"highPriceVolume":0,"avgLowPrice":2190,"lowPriceVolume":31},"5300":{"avgHighPrice":53617,"highPriceVolume":48,"avgLowPrice":53515,"lowPriceVolume":50},"5301":{"avgHighPrice":5907,"highPriceVolume":23,"avgLowPrice":5995,"lowPriceVolume":7},"5302":{"avgHighPrice":null,"highPriceVolume":0,"avgLowPrice":261,"lowPriceVolume":5},"5304":{"avgHighPrice":14536,"highPriceVolume":8,"avgLowPrice":14536,"lowPriceVolume":49},"5307":{"avgHighPrice":null,"highPriceVolume":0,"avgLowPrice":4,"lowPriceVolume":824},"5308":{"avgHighPrice":null,"highPriceVolume":0,"avgLowPrice":6,"lowPriceVolume":500},"5310":{"avgHighPrice":9,"highPriceVolume":300,"avgLowPrice":5,"lowPriceVolume":135},"5311":{"avgHighPrice":null,"highPriceVolume":0,"avgLowPrice":74,"lowPriceVolume":29},"5313":{"avgHighPrice":null,"highPriceVolume":0,"avgLowPrice":85,"lowPriceVolume":6},"5314":{"avgHighPrice":null,"highPriceVolume":0,"avgLowPrice":4250,"lowPriceVolume":50},"5315":{"avgHighPrice":null,"highPriceVolume":0,"avgLowPrice":29500,"lowPriceVolume":20},"5316":{"avgHighPrice":null,"highPriceVolume":0,"avgLowPrice":94260,"lowPriceVolume":27},"5318":{"avgHighPrice":1,"highPriceVolume":900,"avgLowPrice":null,"lowPriceVolume":0},"5319":{"avgHighPrice":1,"highPriceVolume":6,"avgLowPrice":null,"lowPriceVolume":0},"5320":{"avgHighPrice":null,"highPriceVolume":0,"avgLowPrice":6,"lowPriceVolume":107},"5321":{"avgHighPrice":null,"highPriceVolume":0,"avgLowPrice":215,"lowPriceVolume":772},"5323":{"avgHighPrice":10,"highPriceVolume":1,"avgLowPrice":null,"lowPriceVolume":0},"5324":{"avgHighPrice":1,"highPriceVolume":40,"avgLowPrice":null,"lowPriceVolume":0},"5329":{"avgHighPrice":123,"highPriceVolume":1,"avgLowPrice":null,"lowPriceVolume":0},"5341":{"avgHighPrice":88,"highPriceVolume":2,"avgLowPrice":null,"lowPriceVolume":0},"5343":{"avgHighPrice":148,"highPriceVolume":1,"avgLowPrice":null,"lowPriceVolume":0},"5350":{"avgHighPrice":9,"highPriceVolume":5,"avgLowPrice":null,"lowPriceVolume":0},"5372":{"avgHighPrice":5240,"highPriceVolume":269,"avgLowPrice":null,"lowPriceVolume":0},"5373":{"avgHighPrice":31617,"highPriceVolume":68,"avgLowPrice":null,"lowPriceVolume":0},"5374":{"avgHighPrice":99000,"highPriceVolume":10,"avgLowPrice":96543,"lowPriceVolume":4},"5396":{"avgHighPrice":1429,"highPriceVolume":308,"avgLowPrice":null,"lowPriceVolume":0},"5418":{"avgHighPrice":2,"highPriceVolume":12,"avgLowPrice":3,"lowPriceVolume":1010},"5478":{"avgHighPrice":null,"highPriceVolume":0,"avgLowPrice":4892,"lowPriceVolume":56},"5501":{"avgHighPrice":2688,"highPriceVolume":7,"avgLowPrice":null,"lowPriceVolume":0},"5502":{"avgHighPrice":24852,"highPriceVolume":42,"avgLowPrice":null,"lowPriceVolume":0},"5503":{"avgHighPrice":1337,"highPriceVolume":20,"avgLowPrice":null,"lowPriceVolume":0},"5504":{"avgHighPrice":null,"highPriceVolume":0,"avgLowPrice":54,"lowPriceVolume":1},"5525":{"avgHighPrice":90,"highPriceVolume":1,"avgLowPrice":86,"lowPriceVolume":393},"5527":{"avgHighPrice":88,"highPriceVolume":1,"avgLowPrice":null,"lowPriceVolume":0},"5667":{"avgHighPrice":null,"highPriceVolume":0,"avgLowPrice":256,"lowPriceVolume":35},"5698":{"avgHighPrice":17331,"highPriceVolume":1,"avgLowPrice":17331,"lowPriceVolume":20},"5755":{"avgHighPrice":499,"highPriceVolume":1,"avgLowPrice":null,"lowPriceVolume":0},"5933":{"avgHighPrice":1500,"highPriceVolume":36,"avgLowPrice":null,"lowPriceVolume":0},"5935":{"avgHighPrice":null,"highPriceVolume":0,"avgLowPrice":198,"lowPriceVolume":58},"5940":{"avgHighPrice":4195,"highPriceVolume":201,"avgLowPrice":4000,"lowPriceVolume":16},"5952":{"avgHighPrice":4972,"highPriceVolume":30,"avgLowPrice":4581,"lowPriceVolume":4},"5970":{"avgHighPrice":null,"highPriceVolume":0,"avgLowPrice":62,"lowPriceVolume":130},"5972":{"avgHighPrice":1979,"highPriceVolume":315,"avgLowPrice":1902,"lowPriceVolume":80},"5974":{"avgHighPrice":2195,"highPriceVolume":6,"avgLowPrice":2190,"lowPriceVolume":1247},"5982":{"avgHighPrice":18,"highPriceVolume":22,"avgLowPrice":18,"lowPriceVolume":179},"5998":{"avgHighPrice":null,"highPriceVolume":0,"avgLowPrice":731,"lowPriceVolume":1},"6010":{"avgHighPrice":null,"highPriceVolume":0,"avgLowPrice":200,"lowPriceVolume":8},"6016":{"avgHighPrice":1773,"highPriceVolume":1,"avgLowPrice":1761,"lowPriceVolume":263},"6018":{"avgHighPrice":null,"highPriceVolume":0,"avgLowPrice":243,"lowPriceVolume":809},"6034":{"avgHighPrice":null,"highPriceVolume":0,"avgLowPrice":71,"lowPriceVolume":56},"6045":{"avgHighPrice":null,"highPriceVolume":0,"avgLowPrice":18,"lowPriceVolume":30},"6055":{"avgHighPrice":269,"highPriceVolume":2,"avgLowPrice":null,"lowPriceVolume":0},"6281":{"avgHighPrice":null,"highPriceVolume":0,"avgLowPrice":300,"lowPriceVolume":1},"6285":{"avgHighPrice":null,"highPriceVolume":0,"avgLowPrice":1103,"lowPriceVolume":10},"6291":{"avgHighPrice":null,"highPriceVolume":0,"avgLowPrice":219,"lowPriceVolume":20},"6299":{"avgHighPrice":null,"highPriceVolume":0,"avgLowPrice":405,"lowPriceVolume":1},"6319":{"avgHighPrice":null,"highPriceVolume":0,"avgLowPrice":666,"lowPriceVolume":15},"6324":{"avgHighPrice":581,"highPriceVolume":1,"avgLowPrice":null,"lowPriceVolume":0},"6326":{"avgHighPrice":null,"highPriceVolume":0,"avgLowPrice":133,"lowPriceVolume":11},"6328":{"avgHighPrice":453,"highPriceVolume":1,"avgLowPrice":327,"lowPriceVolume":2},"6332":{"avgHighPrice":266,"highPriceVolume":101,"avgLowPrice":266,"lowPriceVolume":13889},"6333":{"avgHighPrice":null,"highPriceVolume":0,"avgLowPrice":139,"lowPriceVolume":3},"6524":{"avgHighPrice":null,"highPriceVolume":0,"avgLowPrice":391322,"lowPriceVolume":1},"6528":{"avgHighPrice":null,"highPriceVolume":0,"avgLowPrice":198995,"lowPriceVolume":1},"6568":{"avgHighPrice":null,"highPriceVolume":0,"avgLowPrice":535000,"lowPriceVolume":1},"6585":{"avgHighPrice":2589126,"highPriceVolume":3,"avgLowPrice":2520907,"lowPriceVolume":2},"6609":{"avgHighPrice":null,"highPriceVolume":0,"avgLowPrice":1200,"lowPriceVolume":1},"6685":{"avgHighPrice":8187,"highPriceVolume":1551,"avgLowPrice":8150,"lowPriceVolume":77},"6687":{"avgHighPrice":5850,"highPriceVolume":21,"avgLowPrice":null,"lowPriceVolume":0},"6729":{"avgHighPrice":null,"highPriceVolume":0,"avgLowPrice":14242,"lowPriceVolume":1},"6731":{"avgHighPrice":784852,"highPriceVolume":1,"avgLowPrice":null,"lowPriceVolume":0},"6733":{"avgHighPrice":null,"highPriceVolume":0,"avgLowPrice":2768682,"lowPriceVolume":1},"6737":{"avgHighPrice":3303257,"highPriceVolume":1,"avgLowPrice":null,"lowPriceVolume":0},"6739":{"avgHighPrice":89696,"highPriceVolume":1,"avgLowPrice":null,"lowPriceVolume":0},"6922":{"avgHighPrice":834849,"highPriceVolume":1,"avgLowPrice":null,"lowPriceVolume":0},"7058":{"avgHighPrice":null,"highPriceVolume":0,"avgLowPrice":846,"lowPriceVolume":55},"7060":{"avgHighPrice":1510,"highPriceVolume":719,"avgLowPrice":1437,"lowPriceVolume":18},"7158":{"avgHighPrice":null,"highPriceVolume":0,"avgLowPrice":131509,"lowPriceVolume":1},"7188":{"avgHighPrice":71,"highPriceVolume":2,"avgLowPrice":null,"lowPriceVolume":0},"7208":{"avgHighPrice":699,"highPriceVolume":1,"avgLowPrice":null,"lowPriceVolume":0},"7218":{"avgHighPrice":636,"highPriceVolume":30,"avgLowPrice":null,"lowPriceVolume":0},"7329":{"avgHighPrice":null,"highPriceVolume":0,"avgLowPrice":63,"lowPriceVolume":9},"7342":{"avgHighPrice":33051,"highPriceVolume":1,"avgLowPrice":null,"lowPriceVolume":0},"7348":{"avgHighPrice":null,"highPriceVolume":0,"avgLowPrice":32504,"lowPriceVolume":1},"7366":{"avgHighPrice":13705,"highPriceVolume":1,"avgLowPrice":null,"lowPriceVolume":0},"7398":{"avgHighPrice":48805,"highPriceVolume":2,"avgLowPrice":null,"lowPriceVolume":0},"7399":{"avgHighPrice":73061,"highPriceVolume":2,"avgLowPrice":null,"lowPriceVolume":0},"7400":{"avgHighPrice":10992,"highPriceVolume":1,"avgLowPrice":null,"lowPriceVolume":0},"7416":{"avgHighPrice":null,"highPriceVolume":0,"avgLowPrice":6918,"lowPriceVolume":110},"7418":{"avgHighPrice":null,"highPriceVolume":0,"avgLowPrice":6188,"lowPriceVolume":137},"7936":{"avgHighPrice":1,"highPriceVolume":155729,"avgLowPrice":null,"lowPriceVolume":0},"7944":{"avgHighPrice":216,"highPriceVolume":260,"avgLowPrice":211,"lowPriceVolume":697},"7946":{"avgHighPrice":255,"highPriceVolume":100,"avgLowPrice":null,"lowPriceVolume":0},"8007":{"avgHighPrice":590,"highPriceVolume":294,"avgLowPrice":580,"lowPriceVolume":1430},"8009":{"avgHighPrice":629,"highPriceVolume":652,"avgLowPrice":626,"lowPriceVolume":1},"8010":{"avgHighPrice":675,"highPriceVolume":38,"avgLowPrice":null,"lowPriceVolume":0},"8011":{"avgHighPrice":475,"highPriceVolume":3,"avgLowPrice":null,"lowPriceVolume":0},"8012":{"avgHighPrice":450,"highPriceVolume":1,"avgLowPrice":null,"lowPriceVolume":0},"8013":{"avgHighPrice":671,"highPriceVolume":2040,"avgLowPrice":671,"lowPriceVolume":100},"8015":{"avgHighPrice":971,"highPriceVolume":200,"avgLowPrice":null,"lowPriceVolume":0},"8423":{"avgHighPrice":null,"highPriceVolume":0,"avgLowPrice":13400,"lowPriceVolume":7},"8778":{"avgHighPrice":527,"highPriceVolume":104,"avgLowPrice":509,"lowPriceVolume":2694},"8780":{"avgHighPrice":854,"highPriceVolume":208,"avgLowPrice":838,"lowPriceVolume":1112},"8782":{"avgHighPrice":2070,"highPriceVolume":189,"avgLowPrice":2060,"lowPriceVolume":179},"8784":{"avgHighPrice":137669,"highPriceVolume":7,"avgLowPrice":137669,"lowPriceVolume":4},"8786":{"avgHighPrice":338998,"highPriceVolume":7,"avgLowPrice":338998,"lowPriceVolume":2},"8788":{"avgHighPrice":998889,"highPriceVolume":4,"avgLowPrice":null,"lowPriceVolume":0},"8790":{"avgHighPrice":447,"highPriceVolume":5,"avgLowPrice":412,"lowPriceVolume":8},"8792":{"avgHighPrice":null,"highPriceVolume":0,"avgLowPrice":1011,"lowPriceVolume":5},"8880":{"avgHighPrice":3296,"highPriceVolume":1,"avgLowPrice":null,"lowPriceVolume":0},"8882":{"avgHighPrice":6,"highPriceVolume":9000,"avgLowPrice":null,"lowPriceVolume":0},"9075":{"avgHighPrice":95,"highPriceVolume":2483,"avgLowPrice":97,"lowPriceVolume":27629},"9143":{"avgHighPrice":null,"highPriceVolume":0,"avgLowPrice":168,"lowPriceVolume":5968},"9144":{"avgHighPrice":null,"highPriceVolume":0,"avgLowPrice":110,"lowPriceVolume":755},"9185":{"avgHighPrice":9568,"highPriceVolume":3,"avgLowPrice":9204,"lowPriceVolume":41},"9189":{"avgHighPrice":null,"highPriceVolume":0,"avgLowPrice":8,"lowPriceVolume":27},"9190":{"avgHighPrice":33,"highPriceVolume":30,"avgLowPrice":null,"lowPriceVolume":0},"9191":{"avgHighPrice":null,"highPriceVolume":0,"avgLowPrice":96,"lowPriceVolume":56},"9192":{"avgHighPrice":157,"highPriceVolume":588,"avgLowPrice":154,"lowPriceVolume":603},"9193":{"avgHighPrice":529,"highPriceVolume":169,"avgLowPrice":529,"lowPriceVolume":1261},"9194":{"avgHighPrice":null,"highPriceVolume":0,"avgLowPrice":8190,"lowPriceVolume":1049},"9242":{"avgHighPrice":166,"highPriceVolume":3300,"avgLowPrice":null,"lowPriceVolume":0},"9243":{"avgHighPrice":142,"highPriceVolume":2500,"avgLowPrice":137,"lowPriceVolume":25063},"9244":{"avgHighPrice":522,"highPriceVolume":555,"avgLowPrice":505,"lowPriceVolume":613},"9245":{"avgHighPrice":null,"highPriceVolume":0,"avgLowPrice":8599,"lowPriceVolume":9856},"9339":{"avgHighPrice":null,"highPriceVolume":0,"avgLowPrice":273,"lowPriceVolume":830},"9342":{"avgHighPrice":null,"highPriceVolume":0,"avgLowPrice":8550,"lowPriceVolume":28},"9381":{"avgHighPrice":159,"highPriceVolume":67,"avgLowPrice":159,"lowPriceVolume":188},"9419":{"avgHighPrice":1499,"highPriceVolume":2,"avgLowPrice":null,"lowPriceVolume":0},"9469":{"avgHighPrice":311211,"highPriceVolume":1,"avgLowPrice":null,"lowPriceVolume":0},"9978":{"avgHighPrice":null,"highPriceVolume":0,"avgLowPrice":45,"lowPriceVolume":3},"10006":{"avgHighPrice":22,"highPriceVolume":2,"avgLowPrice":null,"lowPriceVolume":0},"10008":{"avgHighPrice":60,"highPriceVolume":5,"avgLowPrice":null,"lowPriceVolume":0},"10010":{"avgHighPrice":7,"highPriceVolume":1,"avgLowPrice":null,"lowPriceVolume":0},"10012":{"avgHighPrice":34,"highPriceVolume":6,"avgLowPrice":null,"lowPriceVolume":0},"10033":{"avgHighPrice":805,"highPriceVolume":20,"avgLowPrice":null,"lowPriceVolume":0},"10034":{"avgHighPrice":null,"highPriceVolume":0,"avgLowPrice":1215,"lowPriceVolume":200},"10071":{"avgHighPrice":null,"highPriceVolume":0,"avgLowPrice":500,"lowPriceVolume":1},"10103":{"avgHighPrice":null,"highPriceVolume":0,"avgLowPrice":405,"lowPriceVolume":3},"10115":{"avgHighPrice":87,"highPriceVolume":41,"avgLowPrice":null,"lowPriceVolume":0},"10144":{"avgHighPrice":1,"highPriceVolume":1,"avgLowPrice":null,"lowPriceVolume":0},"10148":{"avgHighPrice":304,"highPriceVolume":1,"avgLowPrice":null,"lowPriceVolume":0},"10364":{"avgHighPrice":28709,"highPriceVolume":1,"avgLowPrice":null,"lowPriceVolume":0},"10370":{"avgHighPrice":119168,"highPriceVolume":1,"avgLowPrice":119168,"lowPriceVolume":1},"10372":{"avgHighPrice":229419,"highPriceVolume":1,"avgLowPrice":229419,"lowPriceVolume":1},"10376":{"avgHighPrice":null,"highPriceVolume":0,"avgLowPrice":16407,"lowPriceVolume":1},"10378":{"avgHighPrice":null,"highPriceVolume":0,"avgLowPrice":101724,"lowPriceVolume":2},"10380":{"avgHighPrice":180000,"highPriceVolume":1,"avgLowPrice":null,"lowPriceVolume":0},"10386":{"avgHighPrice":103083,"highPriceVolume":2,"avgLowPrice":92083,"lowPriceVolume":1},"10388":{"avgHighPrice":224080,"highPriceVolume":1,"avgLowPrice":218255,"lowPriceVolume":1},"10390":{"avgHighPrice":74128,"highPriceVolume":2,"avgLowPrice":61583,"lowPriceVolume":2},"10450":{"avgHighPrice":16025,"highPriceVolume":1,"avgLowPrice":null,"lowPriceVolume":0},"10456":{"avgHighPrice":19999,"highPriceVolume":1,"avgLowPrice":null,"lowPriceVolume":0},"10476":{"avgHighPrice":5686,"highPriceVolume":26,"avgLowPrice":5689,"lowPriceVolume":145},"10810":{"avgHighPrice":null,"highPriceVolume":0,"avgLowPrice":805,"lowPriceVolume":520},"10828":{"avgHighPrice":48986,"highPriceVolume":2,"avgLowPrice":48122,"lowPriceVolume":10},"10925":{"avgHighPrice":18166,"highPriceVolume":300,"avgLowPrice":17804,"lowPriceVolume":106},"10999":{"avgHighPrice":null,"highPriceVolume":0,"avgLowPrice":604,"lowPriceVolume":4},"11037":{"avgHighPrice":null,"highPriceVolume":0,"avgLowPrice":346604,"lowPriceVolume":1},"11074":{"avgHighPrice":null,"highPriceVolume":0,"avgLowPrice":558,"lowPriceVolume":13},"11076":{"avgHighPrice":768,"highPriceVolume":1,"avgLowPrice":null,"lowPriceVolume":0},"11079":{"avgHighPrice":null,"highPriceVolume":0,"avgLowPrice":887,"lowPriceVolume":1},"11088":{"avgHighPrice":null,"highPriceVolume":0,"avgLowPrice":1234,"lowPriceVolume":7},"11090":{"avgHighPrice":2185,"highPriceVolume":10000,"avgLowPrice":null,"lowPriceVolume":0},"11105":{"avgHighPrice":null,"highPriceVolume":0,"avgLowPrice":11641,"lowPriceVolume":1},"11113":{"avgHighPrice":null,"highPriceVolume":0,"avgLowPrice":12000,"lowPriceVolume":92},"11115":{"avgHighPrice":null,"highPriceVolume":0,"avgLowPrice":11650,"lowPriceVolume":4},"11118":{"avgHighPrice":12345,"highPriceVolume":2,"avgLowPrice":null,"lowPriceVolume":0},"11126":{"avgHighPrice":null,"highPriceVolume":0,"avgLowPrice":12185,"lowPriceVolume":5},"11128":{"avgHighPrice":null,"highPriceVolume":0,"avgLowPrice":2339538,"lowPriceVolume":1},"11133":{"avgHighPrice":2495348,"highPriceVolume":2,"avgLowPrice":2426587,"lowPriceVolume":1},"11212":{"avgHighPrice":3045,"highPriceVolume":260,"avgLowPrice":3036,"lowPriceVolume":1395},"11230":{"avgHighPrice":null,"highPriceVolume":0,"avgLowPrice":1365,"lowPriceVolume":864},"11232":{"avgHighPrice":1767,"highPriceVolume":343,"avgLowPrice":1755,"lowPriceVolume":1323},"11235":{"avgHighPrice":null,"highPriceVolume":0,"avgLowPrice":863419,"lowPriceVolume":1},"11237":{"avgHighPrice":null,"highPriceVolume":0,"avgLowPrice":3062,"lowPriceVolume":3177},"11248":{"avgHighPrice":null,"highPriceVolume":0,"avgLowPrice":3513,"lowPriceVolume":115},"11250":{"avgHighPrice":null,"highPriceVolume":0,"avgLowPrice":4321,"lowPriceVolume":154},"11252":{"avgHighPrice":null,"highPriceVolume":0,"avgLowPrice":21469,"lowPriceVolume":99},"11254":{"avgHighPrice":null,"highPriceVolume":0,"avgLowPrice":36404,"lowPriceVolume":19},"11260":{"avgHighPrice":536,"highPriceVolume":500,"avgLowPrice":511,"lowPriceVolume":9},"11284":{"avgHighPrice":null,"highPriceVolume":0,"avgLowPrice":3504573,"lowPriceVolume":4},"11286":{"avgHighPrice":null,"highPriceVolume":0,"avgLowPrice":3411324,"lowPriceVolume":1},"11802":{"avgHighPrice":null,"highPriceVolume":0,"avgLowPrice":8154226,"lowPriceVolume":1},"11804":{"avgHighPrice":19661222,"highPriceVolume":3,"avgLowPrice":19529258,"lowPriceVolume":1},"11826":{"avgHighPrice":9249259,"highPriceVolume":1,"avgLowPrice":null,"lowPriceVolume":0},"11834":{"avgHighPrice":null,"highPriceVolume":0,"avgLowPrice":16264117,"lowPriceVolume":2},"11840":{"avgHighPrice":261000,"highPriceVolume":1,"avgLowPrice":257503,"lowPriceVolume":10},"11875":{"avgHighPrice":57,"highPriceVolume":6000,"avgLowPrice":null,"lowPriceVolume":0},"11889":{"avgHighPrice":null,"highPriceVolume":0,"avgLowPrice":1366200,"lowPriceVolume":1},"11905":{"avgHighPrice":824602,"highPriceVolume":2,"avgLowPrice":null,"lowPriceVolume":0},"11920":{"avgHighPrice":481532,"highPriceVolume":2,"avgLowPrice":null,"lowPriceVolume":0},"11926":{"avgHighPrice":null,"highPriceVolume":0,"avgLowPrice":3388862,"lowPriceVolume":1},"11936":{"avgHighPrice":1519,"highPriceVolume":250,"avgLowPrice":1502,"lowPriceVolume":2},"11940":{"avgHighPrice":null,"highPriceVolume":0,"avgLowPrice":6,"lowPriceVolume":840},"11943":{"avgHighPrice":null,"highPriceVolume":0,"avgLowPrice":4605,"lowPriceVolume":10},"11951":{"avgHighPrice":500,"highPriceVolume":3,"avgLowPrice":null,"lowPriceVolume":0},"11957":{"avgHighPrice":170,"highPriceVolume":100,"avgLowPrice":null,"lowPriceVolume":0},"11968":{"avgHighPrice":12257,"highPriceVolume":1,"avgLowPrice":12233,"lowPriceVolume":13},"11972":{"avgHighPrice":12539,"highPriceVolume":1,"avgLowPrice":null,"lowPriceVolume":0},"11978":{"avgHighPrice":11043,"highPriceVolume":33,"avgLowPrice":10628,"lowPriceVolume":55},"11980":{"avgHighPrice":13300,"highPriceVolume":27,"avgLowPrice":null,"lowPriceVolume":0},"12000":{"avgHighPrice":2496855,"highPriceVolume":1,"avgLowPrice":2408669,"lowPriceVolume":2},"12002":{"avgHighPrice":null,"highPriceVolume":0,"avgLowPrice":430018,"lowPriceVolume":1},"12237":{"avgHighPrice":null,"highPriceVolume":0,"avgLowPrice":42055,"lowPriceVolume":1},"12273":{"avgHighPrice":64999,"highPriceVolume":1,"avgLowPrice":null,"lowPriceVolume":0},"12283":{"avgHighPrice":null,"highPriceVolume":0,"avgLowPrice":4139,"lowPriceVolume":2},"12285":{"avgHighPrice":null,"highPriceVolume":0,"avgLowPrice":2238,"lowPriceVolume":2},"12293":{"avgHighPrice":null,"highPriceVolume":0,"avgLowPrice":15000,"lowPriceVolume":1},"12297":{"avgHighPrice":4299,"highPriceVolume":1,"avgLowPrice":3900,"lowPriceVolume":2},"12363":{"avgHighPrice":null,"highPriceVolume":0,"avgLowPrice":5555,"lowPriceVolume":1},"12395":{"avgHighPrice":null,"highPriceVolume":0,"avgLowPrice":1000,"lowPriceVolume":2},"12402":{"avgHighPrice":23626,"highPriceVolume":4,"avgLowPrice":null,"lowPriceVolume":0},"12403":{"avgHighPrice":6052,"highPriceVolume":3,"avgLowPrice":null,"lowPriceVolume":0},"12406":{"avgHighPrice":16088,"highPriceVolume":10,"avgLowPrice":15845,"lowPriceVolume":2},"12407":{"avgHighPrice":583,"highPriceVolume":36,"avgLowPrice":null,"lowPriceVolume":0},"12410":{"avgHighPrice":2400,"highPriceVolume":15,"avgLowPrice":null,"lowPriceVolume":0},"12470":{"avgHighPrice":null,"highPriceVolume":0,"avgLowPrice":42352,"lowPriceVolume":1},"12480":{"avgHighPrice":113619,"highPriceVolume":1,"avgLowPrice":null,"lowPriceVolume":0},"12492":{"avgHighPrice":null,"highPriceVolume":0,"avgLowPrice":109805,"lowPriceVolume":1},"12494":{"avgHighPrice":null,"highPriceVolume":0,"avgLowPrice":172255,"lowPriceVolume":1},"12502":{"avgHighPrice":null,"highPriceVolume":0,"avgLowPrice":161942,"lowPriceVolume":2},"12504":{"avgHighPrice":null,"highPriceVolume":0,"avgLowPrice":46365,"lowPriceVolume":1},"12506":{"avgHighPrice":37109,"highPriceVolume":1,"avgLowPrice":null,"lowPriceVolume":0},"12508":{"avgHighPrice":110395,"highPriceVolume":2,"avgLowPrice":null,"lowPriceVolume":0},"12510":{"avgHighPrice":200178,"highPriceVolume":2,"avgLowPrice":196009,"lowPriceVolume":2},"12512":{"avgHighPrice":85000,"highPriceVolume":2,"avgLowPrice":68746,"lowPriceVolume":2},"12520":{"avgHighPrice":null,"highPriceVolume":0,"avgLowPrice":5555,"lowPriceVolume":1},"12526":{"avgHighPrice":null,"highPriceVolume":0,"avgLowPrice":157406,"lowPriceVolume":2},"12596":{"avgHighPrice":null,"highPriceVolume":0,"avgLowPrice":2536854,"lowPriceVolume":1},"12617":{"avgHighPrice":4900,"highPriceVolume":1,"avgLowPrice":null,"lowPriceVolume":0},"12618":{"avgHighPrice":4900,"highPriceVolume":1,"avgLowPrice":null,"lowPriceVolume":0},"12619":{"avgHighPrice":5498,"highPriceVolume":1,"avgLowPrice":null,"lowPriceVolume":0},"12620":{"avgHighPrice":5708,"highPriceVolume":2,"avgLowPrice":null,"lowPriceVolume":0},"12621":{"avgHighPrice":3555,"highPriceVolume":2,"avgLowPrice":null,"lowPriceVolume":0},"12622":{"avgHighPrice":3949,"highPriceVolume":1,"avgLowPrice":null,"lowPriceVolume":0},"12623":{"avgHighPrice":2432,"highPriceVolume":1,"avgLowPrice":2102,"lowPriceVolume":1},"12624":{"avgHighPrice":5000,"highPriceVolume":1,"avgLowPrice":null,"lowPriceVolume":0},"12625":{"avgHighPrice":4886,"highPriceVolume":433,"avgLowPrice":null,"lowPriceVolume":0},"12640":{"avgHighPrice":785,"highPriceVolume":4862,"avgLowPrice":null,"lowPriceVolume":0},"12695":{"avgHighPrice":13923,"highPriceVolume":2072,"avgLowPrice":13878,"lowPriceVolume":67},"12697":{"avgHighPrice":null,"highPriceVolume":0,"avgLowPrice":10302,"lowPriceVolume":10},"12699":{"avgHighPrice":7059,"highPriceVolume":100,"avgLowPrice":7059,"lowPriceVolume":100},"12701":{"avgHighPrice":3491,"highPriceVolume":100,"avgLowPrice":null,"lowPriceVolume":0},"12775":{"avgHighPrice":2228,"highPriceVolume":20,"avgLowPrice":2165,"lowPriceVolume":2},"12777":{"avgHighPrice":null,"highPriceVolume":0,"avgLowPrice":639,"lowPriceVolume":2},"12779":{"avgHighPrice":1193,"highPriceVolume":42,"avgLowPrice":1258,"lowPriceVolume":1},"12780":{"avgHighPrice":1692,"highPriceVolume":15,"avgLowPrice":null,"lowPriceVolume":0},"12782":{"avgHighPrice":830,"highPriceVolume":2,"avgLowPrice":null,"lowPriceVolume":0},"12829":{"avgHighPrice":65336,"highPriceVolume":1,"avgLowPrice":65000,"lowPriceVolume":2},"12831":{"avgHighPrice":1139995,"highPriceVolume":1,"avgLowPrice":null,"lowPriceVolume":0},"12865":{"avgHighPrice":null,"highPriceVolume":0,"avgLowPrice":8015,"lowPriceVolume":1},"12867":{"avgHighPrice":null,"highPriceVolume":0,"avgLowPrice":9832,"lowPriceVolume":1},"12869":{"avgHighPrice":null,"highPriceVolume":0,"avgLowPrice":9850,"lowPriceVolume":1},"12871":{"avgHighPrice":14123,"highPriceVolume":1,"avgLowPrice":null,"lowPriceVolume":0},"12877":{"avgHighPrice":null,"highPriceVolume":0,"avgLowPrice":4132689,"lowPriceVolume":1},"12905":{"avgHighPrice":7500,"highPriceVolume":2,"avgLowPrice":7300,"lowPriceVolume":1},"12913":{"avgHighPrice":10734,"highPriceVolume":2000,"avgLowPrice":null,"lowPriceVolume":0},"12917":{"avgHighPrice":5044,"highPriceVolume":2,"avgLowPrice":null,"lowPriceVolume":0},"12919":{"avgHighPrice":2922,"highPriceVolume":140,"avgLowPrice":null,"lowPriceVolume":0},"12924":{"avgHighPrice":null,"highPriceVolume":0,"avgLowPrice":10700000,"lowPriceVolume":2},"12929":{"avgHighPrice":null,"highPriceVolume":0,"avgLowPrice":3737527,"lowPriceVolume":3},"12932":{"avgHighPrice":null,"highPriceVolume":0,"avgLowPrice":3591023,"lowPriceVolume":4},"12934":{"avgHighPrice":187,"highPriceVolume":27309,"avgLowPrice":182,"lowPriceVolume":29601},"12938":{"avgHighPrice":12788,"highPriceVolume":22,"avgLowPrice":12376,"lowPriceVolume":48},"12988":{"avgHighPrice":6358,"highPriceVolume":1,"avgLowPrice":null,"lowPriceVolume":0},"13149":{"avgHighPrice":17629,"highPriceVolume":1,"avgLowPrice":null,"lowPriceVolume":0},"13155":{"avgHighPrice":12000,"highPriceVolume":1,"avgLowPrice":null,"lowPriceVolume":0},"13163":{"avgHighPrice":650000,"highPriceVolume":2,"avgLowPrice":null,"lowPriceVolume":0},"13169":{"avgHighPrice":495794,"highPriceVolume":1,"avgLowPrice":null,"lowPriceVolume":0},"13190":{"avgHighPrice":13986580,"highPriceVolume":40,"avgLowPrice":14041747,"lowPriceVolume":3},"13233":{"avgHighPrice":2562223,"highPriceVolume":1,"avgLowPrice":null,"lowPriceVolume":0},"13237":{"avgHighPrice":null,"highPriceVolume":0,"avgLowPrice":28826287,"lowPriceVolume":1},"13239":{"avgHighPrice":21721368,"highPriceVolume":4,"avgLowPrice":null,"lowPriceVolume":0},"13249":{"avgHighPrice":27825,"highPriceVolume":6,"avgLowPrice":null,"lowPriceVolume":0},"13265":{"avgHighPrice":1709661,"highPriceVolume":1,"avgLowPrice":null,"lowPriceVolume":0},"13271":{"avgHighPrice":null,"highPriceVolume":0,"avgLowPrice":1708166,"lowPriceVolume":1},"13385":{"avgHighPrice":null,"highPriceVolume":0,"avgLowPrice":4806,"lowPriceVolume":9},"13387":{"avgHighPrice":null,"highPriceVolume":0,"avgLowPrice":7601,"lowPriceVolume":10},"13389":{"avgHighPrice":null,"highPriceVolume":0,"avgLowPrice":6550,"lowPriceVolume":11},"13421":{"avgHighPrice":6,"highPriceVolume":1354,"avgLowPrice":null,"lowPriceVolume":0},"13441":{"avgHighPrice":2211,"highPriceVolume":1583,"avgLowPrice":2139,"lowPriceVolume":834},"13448":{"avgHighPrice":null,"highPriceVolume":0,"avgLowPrice":148,"lowPriceVolume":1},"13475":{"avgHighPrice":null,"highPriceVolume":0,"avgLowPrice":353,"lowPriceVolume":5},"13484":{"avgHighPrice":703,"highPriceVolume":165,"avgLowPrice":703,"lowPriceVolume":1},"13493":{"avgHighPrice":null,"highPriceVolume":0,"avgLowPrice":931,"lowPriceVolume":18},"13496":{"avgHighPrice":null,"highPriceVolume":0,"avgLowPrice":1050,"lowPriceVolume":21},"13502":{"avgHighPrice":null,"highPriceVolume":0,"avgLowPrice":1929,"lowPriceVolume":8},"13508":{"avgHighPrice":1993,"highPriceVolume":1,"avgLowPrice":null,"lowPriceVolume":0},"13511":{"avgHighPrice":null,"highPriceVolume":0,"avgLowPrice":3709,"lowPriceVolume":113},"13576":{"avgHighPrice":15855659,"highPriceVolume":1,"avgLowPrice":null,"lowPriceVolume":0},"19478":{"avgHighPrice":null,"highPriceVolume":0,"avgLowPrice":651754,"lowPriceVolume":2},"19481":{"avgHighPrice":null,"highPriceVolume":0,"avgLowPrice":990420,"lowPriceVolume":1},"19484":{"avgHighPrice":769,"highPriceVolume":60,"avgLowPrice":null,"lowPriceVolume":0},"19544":{"avgHighPrice":null,"highPriceVolume":0,"avgLowPrice":19895000,"lowPriceVolume":2},"19547":{"avgHighPrice":null,"highPriceVolume":0,"avgLowPrice":20056106,"lowPriceVolume":3},"19550":{"avgHighPrice":19960795,"highPriceVolume":1,"avgLowPrice":19803146,"lowPriceVolume":1},"19553":{"avgHighPrice":20124267,"highPriceVolume":1,"avgLowPrice":20124267,"lowPriceVolume":3},"19580":{"avgHighPrice":560,"highPriceVolume":2584,"avgLowPrice":539,"lowPriceVolume":184},"19582":{"avgHighPrice":884,"highPriceVolume":126,"avgLowPrice":862,"lowPriceVolume":310},"19584":{"avgHighPrice":1,"highPriceVolume":5103,"avgLowPrice":null,"lowPriceVolume":0},"19615":{"avgHighPrice":2555,"highPriceVolume":43,"avgLowPrice":null,"lowPriceVolume":0},"19619":{"avgHighPrice":2817,"highPriceVolume":7,"avgLowPrice":null,"lowPriceVolume":0},"19621":{"avgHighPrice":2146,"highPriceVolume":22,"avgLowPrice":2081,"lowPriceVolume":78},"19629":{"avgHighPrice":null,"highPriceVolume":0,"avgLowPrice":3960,"lowPriceVolume":293},"19669":{"avgHighPrice":null,"highPriceVolume":0,"avgLowPrice":812,"lowPriceVolume":1549},"19724":{"avgHighPrice":null,"highPriceVolume":0,"avgLowPrice":7005,"lowPriceVolume":1},"19921":{"avgHighPrice":null,"highPriceVolume":0,"avgLowPrice":331922,"lowPriceVolume":2},"19924":{"avgHighPrice":null,"highPriceVolume":0,"avgLowPrice":202304,"lowPriceVolume":2},"19930":{"avgHighPrice":436624,"highPriceVolume":1,"avgLowPrice":396987,"lowPriceVolume":1},"19933":{"avgHighPrice":222788,"highPriceVolume":2,"avgLowPrice":213846,"lowPriceVolume":2},"20071":{"avgHighPrice":3604868,"highPriceVolume":1,"avgLowPrice":null,"lowPriceVolume":0},"20113":{"avgHighPrice":null,"highPriceVolume":0,"avgLowPrice":2666,"lowPriceVolume":1},"20229":{"avgHighPrice":8799,"highPriceVolume":1,"avgLowPrice":6953,"lowPriceVolume":1},"20232":{"avgHighPrice":13849,"highPriceVolume":2,"avgLowPrice":null,"lowPriceVolume":0},"20595":{"avgHighPrice":null,"highPriceVolume":0,"avgLowPrice":225935,"lowPriceVolume":2},"20716":{"avgHighPrice":753520,"highPriceVolume":1,"avgLowPrice":null,"lowPriceVolume":0},"20718":{"avgHighPrice":2740,"highPriceVolume":30,"avgLowPrice":null,"lowPriceVolume":0},"20736":{"avgHighPrice":null,"highPriceVolume":0,"avgLowPrice":11078,"lowPriceVolume":1},"20739":{"avgHighPrice":44895,"highPriceVolume":1,"avgLowPrice":null,"lowPriceVolume":0},"21000":{"avgHighPrice":14471132,"highPriceVolume":1,"avgLowPrice":null,"lowPriceVolume":0},"21003":{"avgHighPrice":null,"highPriceVolume":0,"avgLowPrice":96034423,"lowPriceVolume":2},"21012":{"avgHighPrice":null,"highPriceVolume":0,"avgLowPrice":39798334,"lowPriceVolume":2},"21015":{"avgHighPrice":null,"highPriceVolume":0,"avgLowPrice":13151160,"lowPriceVolume":1},"21034":{"avgHighPrice":null,"highPriceVolume":0,"avgLowPrice":18192738,"lowPriceVolume":1},"21047":{"avgHighPrice":null,"highPriceVolume":0,"avgLowPrice":47000,"lowPriceVolume":3},"21146":{"avgHighPrice":978,"highPriceVolume":43,"avgLowPrice":null,"lowPriceVolume":0},"21166":{"avgHighPrice":2930,"highPriceVolume":3,"avgLowPrice":null,"lowPriceVolume":0},"21177":{"avgHighPrice":810,"highPriceVolume":8,"avgLowPrice":null,"lowPriceVolume":0},"21183":{"avgHighPrice":3621,"highPriceVolume":16,"avgLowPrice":3500,"lowPriceVolume":18},"21202":{"avgHighPrice":521312,"highPriceVolume":1,"avgLowPrice":null,"lowPriceVolume":0},"21298":{"avgHighPrice":null,"highPriceVolume":0,"avgLowPrice":705342,"lowPriceVolume":1},"21301":{"avgHighPrice":null,"highPriceVolume":0,"avgLowPrice":1332655,"lowPriceVolume":1},"21304":{"avgHighPrice":null,"highPriceVolume":0,"avgLowPrice":928322,"lowPriceVolume":1},"21326":{"avgHighPrice":200,"highPriceVolume":4054,"avgLowPrice":199,"lowPriceVolume":3917},"21336":{"avgHighPrice":1089,"highPriceVolume":5,"avgLowPrice":null,"lowPriceVolume":0},"21347":{"avgHighPrice":3367,"highPriceVolume":1801,"avgLowPrice":3370,"lowPriceVolume":14801},"21350":{"avgHighPrice":229,"highPriceVolume":9900,"avgLowPrice":null,"lowPriceVolume":0},"21387":{"avgHighPrice":null,"highPriceVolume":0,"avgLowPrice":51000,"lowPriceVolume":1},"21483":{"avgHighPrice":550,"highPriceVolume":80,"avgLowPrice":null,"lowPriceVolume":0},"21486":{"avgHighPrice":null,"highPriceVolume":0,"avgLowPrice":66,"lowPriceVolume":1},"21488":{"avgHighPrice":null,"highPriceVolume":0,"avgLowPrice":435,"lowPriceVolume":2},"21555":{"avgHighPrice":null,"highPriceVolume":0,"avgLowPrice":41,"lowPriceVolume":13},"21622":{"avgHighPrice":98,"highPriceVolume":7315,"avgLowPrice":null,"lowPriceVolume":0},"21739":{"avgHighPrice":null,"highPriceVolume":0,"avgLowPrice":22750,"lowPriceVolume":5},"21742":{"avgHighPrice":null,"highPriceVolume":0,"avgLowPrice":3499254,"lowPriceVolume":1},"21754":{"avgHighPrice":318,"highPriceVolume":50,"avgLowPrice":237,"lowPriceVolume":322},"21802":{"avgHighPrice":788,"highPriceVolume":41,"avgLowPrice":763,"lowPriceVolume":5},"21804":{"avgHighPrice":155622,"highPriceVolume":4,"avgLowPrice":150222,"lowPriceVolume":2},"21807":{"avgHighPrice":498801,"highPriceVolume":2,"avgLowPrice":498801,"lowPriceVolume":2},"21817":{"avgHighPrice":null,"highPriceVolume":0,"avgLowPrice":43014,"lowPriceVolume":182},"21820":{"avgHighPrice":175,"highPriceVolume":18720,"avgLowPrice":171,"lowPriceVolume":6245},"21880":{"avgHighPrice":328,"highPriceVolume":52870,"avgLowPrice":323,"lowPriceVolume":607},"21902":{"avgHighPrice":707195,"highPriceVolume":2,"avgLowPrice":691967,"lowPriceVolume":3},"21930":{"avgHighPrice":null,"highPriceVolume":0,"avgLowPrice":2537,"lowPriceVolume":3128},"21932":{"avgHighPrice":2848,"highPriceVolume":300,"avgLowPrice":null,"lowPriceVolume":0},"21940":{"avgHighPrice":2816,"highPriceVolume":197,"avgLowPrice":2816,"lowPriceVolume":197},"21944":{"avgHighPrice":2875,"highPriceVolume":830,"avgLowPrice":2852,"lowPriceVolume":1050},"21946":{"avgHighPrice":2733,"highPriceVolume":478,"avgLowPrice":2685,"lowPriceVolume":6719},"21948":{"avgHighPrice":null,"highPriceVolume":0,"avgLowPrice":2131,"lowPriceVolume":22},"21969":{"avgHighPrice":2679,"highPriceVolume":6123,"avgLowPrice":null,"lowPriceVolume":0},"22003":{"avgHighPrice":15546568,"highPriceVolume":1,"avgLowPrice":null,"lowPriceVolume":0},"22111":{"avgHighPrice":null,"highPriceVolume":0,"avgLowPrice":99166,"lowPriceVolume":10},"22118":{"avgHighPrice":null,"highPriceVolume":0,"avgLowPrice":324,"lowPriceVolume":1},"22124":{"avgHighPrice":null,"highPriceVolume":0,"avgLowPrice":22760,"lowPriceVolume":1684},"22209":{"avgHighPrice":21750,"highPriceVolume":18,"avgLowPrice":null,"lowPriceVolume":0},"22246":{"avgHighPrice":null,"highPriceVolume":0,"avgLowPrice":4088713,"lowPriceVolume":1},"22257":{"avgHighPrice":null,"highPriceVolume":0,"avgLowPrice":112,"lowPriceVolume":7},"22275":{"avgHighPrice":null,"highPriceVolume":0,"avgLowPrice":4421,"lowPriceVolume":1},"22278":{"avgHighPrice":3870,"highPriceVolume":1,"avgLowPrice":null,"lowPriceVolume":0},"22281":{"avgHighPrice":null,"highPriceVolume":0,"avgLowPrice":10103,"lowPriceVolume":2},"22438":{"avgHighPrice":31364999,"highPriceVolume":3,"avgLowPrice":30589231,"lowPriceVolume":1},"22446":{"avgHighPrice":10461,"highPriceVolume":110,"avgLowPrice":null,"lowPriceVolume":0},"22461":{"avgHighPrice":19555,"highPriceVolume":4,"avgLowPrice":18994,"lowPriceVolume":5},"22477":{"avgHighPrice":36326022,"highPriceVolume":1,"avgLowPrice":null,"lowPriceVolume":0},"22481":{"avgHighPrice":null,"highPriceVolume":0,"avgLowPrice":15848434,"lowPriceVolume":2},"22547":{"avgHighPrice":null,"highPriceVolume":0,"avgLowPrice":14530000,"lowPriceVolume":1},"22557":{"avgHighPrice":486457,"highPriceVolume":1,"avgLowPrice":null,"lowPriceVolume":0},"22593":{"avgHighPrice":101,"highPriceVolume":700,"avgLowPrice":null,"lowPriceVolume":0},"22595":{"avgHighPrice":103,"highPriceVolume":200,"avgLowPrice":103,"lowPriceVolume":500},"22597":{"avgHighPrice":100,"highPriceVolume":50,"avgLowPrice":100,"lowPriceVolume":500},"22599":{"avgHighPrice":1222,"highPriceVolume":2,"avgLowPrice":null,"lowPriceVolume":0},"22601":{"avgHighPrice":1231,"highPriceVolume":1,"avgLowPrice":null,"lowPriceVolume":0},"22780":{"avgHighPrice":null,"highPriceVolume":0,"avgLowPrice":1331,"lowPriceVolume":14},"22786":{"avgHighPrice":null,"highPriceVolume":0,"avgLowPrice":7601,"lowPriceVolume":156},"22804":{"avgHighPrice":null,"highPriceVolume":0,"avgLowPrice":7176,"lowPriceVolume":100},"22856":{"avgHighPrice":22790,"highPriceVolume":11,"avgLowPrice":null,"lowPriceVolume":0},"22859":{"avgHighPrice":22000,"highPriceVolume":10,"avgLowPrice":null,"lowPriceVolume":0},"22869":{"avgHighPrice":null,"highPriceVolume":0,"avgLowPrice":20584,"lowPriceVolume":8},"22871":{"avgHighPrice":null,"highPriceVolume":0,"avgLowPrice":20565,"lowPriceVolume":1},"22877":{"avgHighPrice":null,"highPriceVolume":0,"avgLowPrice":175540,"lowPriceVolume":8},"22879":{"avgHighPrice":null,"highPriceVolume":0,"avgLowPrice":12710,"lowPriceVolume":8},"22887":{"avgHighPrice":4468,"highPriceVolume":1,"avgLowPrice":null,"lowPriceVolume":0},"22929":{"avgHighPrice":855,"highPriceVolume":100,"avgLowPrice":841,"lowPriceVolume":331},"22951":{"avgHighPrice":null,"highPriceVolume":0,"avgLowPrice":326348,"lowPriceVolume":5},"22954":{"avgHighPrice":null,"highPriceVolume":0,"avgLowPrice":818372,"lowPriceVolume":2},"22957":{"avgHighPrice":null,"highPriceVolume":0,"avgLowPrice":315000,"lowPriceVolume":1},"22975":{"avgHighPrice":2968173,"highPriceVolume":1,"avgLowPrice":2891638,"lowPriceVolume":2},"22978":{"avgHighPrice":64043233,"highPriceVolume":1,"avgLowPrice":63290251,"lowPriceVolume":3},"22983":{"avgHighPrice":13250000,"highPriceVolume":2,"avgLowPrice":12882618,"lowPriceVolume":2},"23113":{"avgHighPrice":145674,"highPriceVolume":2,"avgLowPrice":null,"lowPriceVolume":0},"23312":{"avgHighPrice":10400,"highPriceVolume":4,"avgLowPrice":null,"lowPriceVolume":0},"23315":{"avgHighPrice":10000,"highPriceVolume":4,"avgLowPrice":null,"lowPriceVolume":0},"23318":{"avgHighPrice":3800,"highPriceVolume":4,"avgLowPrice":null,"lowPriceVolume":0},"23348":{"avgHighPrice":null,"highPriceVolume":0,"avgLowPrice":43713,"lowPriceVolume":1},"23351":{"avgHighPrice":4149860,"highPriceVolume":1,"avgLowPrice":null,"lowPriceVolume":0},"23387":{"avgHighPrice":4400,"highPriceVolume":1,"avgLowPrice":null,"lowPriceVolume":0},"23389":{"avgHighPrice":null,"highPriceVolume":0,"avgLowPrice":455358,"lowPriceVolume":2},"23490":{"avgHighPrice":148638,"highPriceVolume":1,"avgLowPrice":146002,"lowPriceVolume":8},"23499":{"avgHighPrice":null,"highPriceVolume":0,"avgLowPrice":34750,"lowPriceVolume":73},"23517":{"avgHighPrice":null,"highPriceVolume":0,"avgLowPrice":17489,"lowPriceVolume":60},"23685":{"avgHighPrice":19979,"highPriceVolume":386,"avgLowPrice":null,"lowPriceVolume":0},"23691":{"avgHighPrice":null,"highPriceVolume":0,"avgLowPrice":9800,"lowPriceVolume":6},"23694":{"avgHighPrice":5187,"highPriceVolume":1,"avgLowPrice":4749,"lowPriceVolume":16},"23697":{"avgHighPrice":null,"highPriceVolume":0,"avgLowPrice":3840,"lowPriceVolume":20},"23709":{"avgHighPrice":6183,"highPriceVolume":4,"avgLowPrice":null,"lowPriceVolume":0},"23721":{"avgHighPrice":null,"highPriceVolume":0,"avgLowPrice":4071,"lowPriceVolume":20},"23733":{"avgHighPrice":5971,"highPriceVolume":62,"avgLowPrice":null,"lowPriceVolume":0},"23736":{"avgHighPrice":4597,"highPriceVolume":100,"avgLowPrice":null,"lowPriceVolume":0},"23739":{"avgHighPrice":2957,"highPriceVolume":7,"avgLowPrice":2714,"lowPriceVolume":17},"23956":{"avgHighPrice":null,"highPriceVolume":0,"avgLowPrice":8047160,"lowPriceVolume":1},"23959":{"avgHighPrice":3683987,"highPriceVolume":1,"avgLowPrice":3585691,"lowPriceVolume":2},"24187":{"avgHighPrice":749411,"highPriceVolume":6,"avgLowPrice":null,"lowPriceVolume":0},"24229":{"avgHighPrice":null,"highPriceVolume":0,"avgLowPrice":781983,"lowPriceVolume":4},"24251":{"avgHighPrice":17533,"highPriceVolume":6,"avgLowPrice":17072,"lowPriceVolume":7},"24268":{"avgHighPrice":17154586,"highPriceVolume":1,"avgLowPrice":16616043,"lowPriceVolume":1},"24460":{"avgHighPrice":510204,"highPriceVolume":1,"avgLowPrice":null,"lowPriceVolume":0},"24463":{"avgHighPrice":2400000,"highPriceVolume":1,"avgLowPrice":null,"lowPriceVolume":0},"24585":{"avgHighPrice":48421,"highPriceVolume":1,"avgLowPrice":null,"lowPriceVolume":0},"24589":{"avgHighPrice":133,"highPriceVolume":200,"avgLowPrice":129,"lowPriceVolume":8},"24592":{"avgHighPrice":110,"highPriceVolume":1568,"avgLowPrice":106,"lowPriceVolume":11},"24595":{"avgHighPrice":59,"highPriceVolume":1000,"avgLowPrice":53,"lowPriceVolume":73},"24598":{"avgHighPrice":2111,"highPriceVolume":1156,"avgLowPrice":2055,"lowPriceVolume":1450},"24607":{"avgHighPrice":279,"highPriceVolume":2600,"avgLowPrice":268,"lowPriceVolume":2023},"24613":{"avgHighPrice":49,"highPriceVolume":100,"avgLowPrice":null,"lowPriceVolume":0},"24615":{"avgHighPrice":53,"highPriceVolume":28,"avgLowPrice":null,"lowPriceVolume":0},"24621":{"avgHighPrice":76,"highPriceVolume":6,"avgLowPrice":null,"lowPriceVolume":0},"24635":{"avgHighPrice":24248,"highPriceVolume":2,"avgLowPrice":23742,"lowPriceVolume":3},"24641":{"avgHighPrice":null,"highPriceVolume":0,"avgLowPrice":12287,"lowPriceVolume":1},"24844":{"avgHighPrice":4847597,"highPriceVolume":1,"avgLowPrice":4713403,"lowPriceVolume":1},"24963":{"avgHighPrice":1993,"highPriceVolume":1,"avgLowPrice":1545,"lowPriceVolume":9},"25404":{"avgHighPrice":182285,"highPriceVolume":2,"avgLowPrice":null,"lowPriceVolume":0},"25410":{"avgHighPrice":41515,"highPriceVolume":6,"avgLowPrice":37393,"lowPriceVolume":2},"25413":{"avgHighPrice":94298,"highPriceVolume":1,"avgLowPrice":null,"lowPriceVolume":0},"25416":{"avgHighPrice":177483,"highPriceVolume":4,"avgLowPrice":null,"lowPriceVolume":0},"25766":{"avgHighPrice":null,"highPriceVolume":0,"avgLowPrice":46,"lowPriceVolume":5},"25769":{"avgHighPrice":null,"highPriceVolume":0,"avgLowPrice":145,"lowPriceVolume":198},"25778":{"avgHighPrice":null,"highPriceVolume":0,"avgLowPrice":3305,"lowPriceVolume":7},"25849":{"avgHighPrice":214,"highPriceVolume":6000,"avgLowPrice":null,"lowPriceVolume":0},"25853":{"avgHighPrice":430,"highPriceVolume":20457,"avgLowPrice":null,"lowPriceVolume":0},"25862":{"avgHighPrice":null,"highPriceVolume":0,"avgLowPrice":144067567,"lowPriceVolume":1},"25975":{"avgHighPrice":4792481,"highPriceVolume":17,"avgLowPrice":4887679,"lowPriceVolume":92},"25985":{"avgHighPrice":3756404,"highPriceVolume":1,"avgLowPrice":3660923,"lowPriceVolume":1},"26219":{"avgHighPrice":19329352,"highPriceVolume":2,"avgLowPrice":18961135,"lowPriceVolume":5},"26225":{"avgHighPrice":29238,"highPriceVolume":1,"avgLowPrice":null,"lowPriceVolume":0},"26227":{"avgHighPrice":23018,"highPriceVolume":1,"avgLowPrice":null,"lowPriceVolume":0},"26229":{"avgHighPrice":23098,"highPriceVolume":2,"avgLowPrice":null,"lowPriceVolume":0},"26372":{"avgHighPrice":null,"highPriceVolume":0,"avgLowPrice":316701000,"lowPriceVolume":2},"26374":{"avgHighPrice":358497058,"highPriceVolume":1,"avgLowPrice":null,"lowPriceVolume":0},"26376":{"avgHighPrice":null,"highPriceVolume":0,"avgLowPrice":223127723,"lowPriceVolume":1},"26380":{"avgHighPrice":null,"highPriceVolume":0,"avgLowPrice":115564704,"lowPriceVolume":1},"26390":{"avgHighPrice":88498,"highPriceVolume":3,"avgLowPrice":87250,"lowPriceVolume":12},"27202":{"avgHighPrice":2170,"highPriceVolume":70,"avgLowPrice":null,"lowPriceVolume":0},"27226":{"avgHighPrice":12000000,"highPriceVolume":1,"avgLowPrice":11544449,"lowPriceVolume":1},"27232":{"avgHighPrice":null,"highPriceVolume":0,"avgLowPrice":31850000,"lowPriceVolume":2},"27238":{"avgHighPrice":null,"highPriceVolume":0,"avgLowPrice":85580669,"lowPriceVolume":2},"27241":{"avgHighPrice":null,"highPriceVolume":0,"avgLowPrice":59089756,"lowPriceVolume":1},"27272":{"avgHighPrice":1686,"highPriceVolume":4,"avgLowPrice":1686,"lowPriceVolume":10},"27616":{"avgHighPrice":null,"highPriceVolume":0,"avgLowPrice":17,"lowPriceVolume":159855},"27629":{"avgHighPrice":3999,"highPriceVolume":101,"avgLowPrice":null,"lowPriceVolume":0},"27632":{"avgHighPrice":null,"highPriceVolume":0,"avgLowPrice":1610,"lowPriceVolume":18},"27638":{"avgHighPrice":null,"highPriceVolume":0,"avgLowPrice":1709,"lowPriceVolume":1},"27641":{"avgHighPrice":105275667,"highPriceVolume":1,"avgLowPrice":null,"lowPriceVolume":0},"27652":{"avgHighPrice":14931556,"highPriceVolume":2,"avgLowPrice":null,"lowPriceVolume":0},"27657":{"avgHighPrice":5535318,"highPriceVolume":1,"avgLowPrice":null,"lowPriceVolume":0},"27670":{"avgHighPrice":null,"highPriceVolume":0,"avgLowPrice":59000,"lowPriceVolume":1},"27690":{"avgHighPrice":37410089,"highPriceVolume":3,"avgLowPrice":36471057,"lowPriceVolume":1},"27897":{"avgHighPrice":null,"highPriceVolume":0,"avgLowPrice":836,"lowPriceVolume":7},"28217":{"avgHighPrice":2135037,"highPriceVolume":1,"avgLowPrice":2053214,"lowPriceVolume":2},"28310":{"avgHighPrice":null,"highPriceVolume":0,"avgLowPrice":51600000,"lowPriceVolume":1},"28313":{"avgHighPrice":28096337,"highPriceVolume":1,"avgLowPrice":28096337,"lowPriceVolume":1},"28334":{"avgHighPrice":null,"highPriceVolume":0,"avgLowPrice":382561,"lowPriceVolume":3},"28338":{"avgHighPrice":null,"highPriceVolume":0,"avgLowPrice":270511000,"lowPriceVolume":1},"28708":{"avgHighPrice":6489888,"highPriceVolume":1,"avgLowPrice":null,"lowPriceVolume":0},"28824":{"avgHighPrice":910,"highPriceVolume":176,"avgLowPrice":null,"lowPriceVolume":0},"28869":{"avgHighPrice":null,"highPriceVolume":0,"avgLowPrice":5695,"lowPriceVolume":1},"28878":{"avgHighPrice":475,"highPriceVolume":600,"avgLowPrice":470,"lowPriceVolume":1008},"28899":{"avgHighPrice":null,"highPriceVolume":0,"avgLowPrice":423,"lowPriceVolume":50},"28924":{"avgHighPrice":379,"highPriceVolume":30334,"avgLowPrice":null,"lowPriceVolume":0},"28936":{"avgHighPrice":2842000,"highPriceVolume":2,"avgLowPrice":null,"lowPriceVolume":0},"28988":{"avgHighPrice":null,"highPriceVolume":0,"avgLowPrice":346885,"lowPriceVolume":1},"28991":{"avgHighPrice":233,"highPriceVolume":1800,"avgLowPrice":223,"lowPriceVolume":1725},"29004":{"avgHighPrice":1895635,"highPriceVolume":1,"avgLowPrice":null,"lowPriceVolume":0},"29007":{"avgHighPrice":1892024,"highPriceVolume":1,"avgLowPrice":null,"lowPriceVolume":0},"29013":{"avgHighPrice":1720697,"highPriceVolume":2,"avgLowPrice":null,"lowPriceVolume":0},"29016":{"avgHighPrice":3976394,"highPriceVolume":1,"avgLowPrice":null,"lowPriceVolume":0},"29025":{"avgHighPrice":10540000,"highPriceVolume":1,"avgLowPrice":10333333,"lowPriceVolume":1},"29067":{"avgHighPrice":null,"highPriceVolume":0,"avgLowPrice":3881000,"lowPriceVolume":1},"29073":{"avgHighPrice":null,"highPriceVolume":0,"avgLowPrice":115011,"lowPriceVolume":1},"29084":{"avgHighPrice":null,"highPriceVolume":0,"avgLowPrice":90002,"lowPriceVolume":1},"29107":{"avgHighPrice":null,"highPriceVolume":0,"avgLowPrice":2401,"lowPriceVolume":2},"29116":{"avgHighPrice":null,"highPriceVolume":0,"avgLowPrice":2449,"lowPriceVolume":131},"29166":{"avgHighPrice":48,"highPriceVolume":2,"avgLowPrice":null,"lowPriceVolume":0},"29307":{"avgHighPrice":5236,"highPriceVolume":60,"avgLowPrice":null,"lowPriceVolume":0},"29409":{"avgHighPrice":null,"highPriceVolume":0,"avgLowPrice":100,"lowPriceVolume":1},"29455":{"avgHighPrice":58000,"highPriceVolume":1,"avgLowPrice":null,"lowPriceVolume":0},"29458":{"avgHighPrice":170,"highPriceVolume":46,"avgLowPrice":null,"lowPriceVolume":0},"29580":{"avgHighPrice":36200000,"highPriceVolume":2,"avgLowPrice":null,"lowPriceVolume":0},"29684":{"avgHighPrice":23687,"highPriceVolume":2,"avgLowPrice":22147,"lowPriceVolume":9},"29784":{"avgHighPrice":2003,"highPriceVolume":10798,"avgLowPrice":2014,"lowPriceVolume":33345},"29796":{"avgHighPrice":50325052,"highPriceVolume":3,"avgLowPrice":50293263,"lowPriceVolume":5},"29801":{"avgHighPrice":null,"highPriceVolume":0,"avgLowPrice":61327922,"lowPriceVolume":2},"29806":{"avgHighPrice":null,"highPriceVolume":0,"avgLowPrice":2023864,"lowPriceVolume":1},"29824":{"avgHighPrice":18200,"highPriceVolume":401,"avgLowPrice":18047,"lowPriceVolume":13},"30066":{"avgHighPrice":null,"highPriceVolume":0,"avgLowPrice":676949,"lowPriceVolume":1},"30068":{"avgHighPrice":1693,"highPriceVolume":50,"avgLowPrice":null,"lowPriceVolume":0},"30070":{"avgHighPrice":null,"highPriceVolume":0,"avgLowPrice":14405819,"lowPriceVolume":2},"30076":{"avgHighPrice":1639506,"highPriceVolume":1,"avgLowPrice":1544775,"lowPriceVolume":1},"30079":{"avgHighPrice":null,"highPriceVolume":0,"avgLowPrice":1105000,"lowPriceVolume":1},"30097":{"avgHighPrice":null,"highPriceVolume":0,"avgLowPrice":6826,"lowPriceVolume":87},"30125":{"avgHighPrice":61333,"highPriceVolume":200,"avgLowPrice":null,"lowPriceVolume":0},"30128":{"avgHighPrice":null,"highPriceVolume":0,"avgLowPrice":43601,"lowPriceVolume":6},"30134":{"avgHighPrice":null,"highPriceVolume":0,"avgLowPrice":14400,"lowPriceVolume":2},"30563":{"avgHighPrice":3362144,"highPriceVolume":2,"avgLowPrice":null,"lowPriceVolume":0},"30619":{"avgHighPrice":4450,"highPriceVolume":30,"avgLowPrice":null,"lowPriceVolume":0},"30631":{"avgHighPrice":null,"highPriceVolume":0,"avgLowPrice":3035006,"lowPriceVolume":1},"30634":{"avgHighPrice":null,"highPriceVolume":0,"avgLowPrice":5859792,"lowPriceVolume":3},"30753":{"avgHighPrice":92295643,"highPriceVolume":1,"avgLowPrice":null,"lowPriceVolume":0},"30756":{"avgHighPrice":91000000,"highPriceVolume":1,"avgLowPrice":null,"lowPriceVolume":0},"30765":{"avgHighPrice":null,"highPriceVolume":0,"avgLowPrice":192750,"lowPriceVolume":10},"30771":{"avgHighPrice":null,"highPriceVolume":0,"avgLowPrice":367,"lowPriceVolume":808},"30775":{"avgHighPrice":null,"highPriceVolume":0,"avgLowPrice":34791,"lowPriceVolume":6},"30800":{"avgHighPrice":344,"highPriceVolume":200,"avgLowPrice":null,"lowPriceVolume":0},"30810":{"avgHighPrice":null,"highPriceVolume":0,"avgLowPrice":194444,"lowPriceVolume":6},"30843":{"avgHighPrice":810,"highPriceVolume":26000,"avgLowPrice":null,"lowPriceVolume":0},"30900":{"avgHighPrice":null,"highPriceVolume":0,"avgLowPrice":314,"lowPriceVolume":1790},"30998":{"avgHighPrice":128,"highPriceVolume":4500,"avgLowPrice":null,"lowPriceVolume":0},"31010":{"avgHighPrice":115,"highPriceVolume":4500,"avgLowPrice":null,"lowPriceVolume":0},"31034":{"avgHighPrice":null,"highPriceVolume":0,"avgLowPrice":11447,"lowPriceVolume":4},"31081":{"avgHighPrice":844062,"highPriceVolume":1,"avgLowPrice":804387,"lowPriceVolume":2},"31088":{"avgHighPrice":null,"highPriceVolume":0,"avgLowPrice":186769004,"lowPriceVolume":2},"31099":{"avgHighPrice":null,"highPriceVolume":0,"avgLowPrice":76467,"lowPriceVolume":6},"31111":{"avgHighPrice":null,"highPriceVolume":0,"avgLowPrice":335,"lowPriceVolume":980},"31115":{"avgHighPrice":52382674,"highPriceVolume":1,"avgLowPrice":null,"lowPriceVolume":0},"31136":{"avgHighPrice":22981018,"highPriceVolume":2,"avgLowPrice":null,"lowPriceVolume":0},"31142":{"avgHighPrice":6981000,"highPriceVolume":2,"avgLowPrice":null,"lowPriceVolume":0},"31248":{"avgHighPrice":null,"highPriceVolume":0,"avgLowPrice":320000,"lowPriceVolume":1},"31406":{"avgHighPrice":null,"highPriceVolume":0,"avgLowPrice":27464,"lowPriceVolume":63},"31432":{"avgHighPrice":3420,"highPriceVolume":33,"avgLowPrice":null,"lowPriceVolume":0},"31435":{"avgHighPrice":3990,"highPriceVolume":34,"avgLowPrice":null,"lowPriceVolume":0},"31443":{"avgHighPrice":815,"highPriceVolume":1,"avgLowPrice":806,"lowPriceVolume":1},"31460":{"avgHighPrice":3688,"highPriceVolume":127,"avgLowPrice":3742,"lowPriceVolume":8},"31487":{"avgHighPrice":2900,"highPriceVolume":99,"avgLowPrice":2900,"lowPriceVolume":156},"31515":{"avgHighPrice":3844,"highPriceVolume":8,"avgLowPrice":null,"lowPriceVolume":0},"31549":{"avgHighPrice":null,"highPriceVolume":0,"avgLowPrice":33700,"lowPriceVolume":5},"31551":{"avgHighPrice":null,"highPriceVolume":0,"avgLowPrice":155011,"lowPriceVolume":2},"31638":{"avgHighPrice":12100,"highPriceVolume":46,"avgLowPrice":12006,"lowPriceVolume":18},"31650":{"avgHighPrice":1950,"highPriceVolume":100,"avgLowPrice":null,"lowPriceVolume":0},"31656":{"avgHighPrice":null,"highPriceVolume":0,"avgLowPrice":860,"lowPriceVolume":1},"31716":{"avgHighPrice":420,"highPriceVolume":500,"avgLowPrice":369,"lowPriceVolume":3294},"31912":{"avgHighPrice":null,"highPriceVolume":0,"avgLowPrice":270,"lowPriceVolume":895},"31961":{"avgHighPrice":null,"highPriceVolume":0,"avgLowPrice":20965253,"lowPriceVolume":3},"31996":{"avgHighPrice":null,"highPriceVolume":0,"avgLowPrice":511001,"lowPriceVolume":6},"32053":{"avgHighPrice":9320,"highPriceVolume":400,"avgLowPrice":null,"lowPriceVolume":0},"32059":{"avgHighPrice":null,"highPriceVolume":0,"avgLowPrice":12100,"lowPriceVolume":100},"32087":{"avgHighPrice":null,"highPriceVolume":0,"avgLowPrice":2161317,"lowPriceVolume":2},"32333":{"avgHighPrice":2854,"highPriceVolume":40,"avgLowPrice":null,"lowPriceVolume":0},"32336":{"avgHighPrice":3228,"highPriceVolume":30,"avgLowPrice":3081,"lowPriceVolume":9},"32349":{"avgHighPrice":6729,"highPriceVolume":1,"avgLowPrice":null,"lowPriceVolume":0},"32352":{"avgHighPrice":7250,"highPriceVolume":20,"avgLowPrice":6988,"lowPriceVolume":11},"32362":{"avgHighPrice":2088,"highPriceVolume":11000,"avgLowPrice":null,"lowPriceVolume":0},"32889":{"avgHighPrice":1254,"highPriceVolume":92,"avgLowPrice":null,"lowPriceVolume":0},"32892":{"avgHighPrice":2400,"highPriceVolume":4,"avgLowPrice":null,"lowPriceVolume":0},"32904":{"avgHighPrice":685,"highPriceVolume":20,"avgLowPrice":null,"lowPriceVolume":0},"33106":{"avgHighPrice":null,"highPriceVolume":0,"avgLowPrice":87,"lowPriceVolume":9},"33109":{"avgHighPrice":null,"highPriceVolume":0,"avgLowPrice":62,"lowPriceVolume":12}},"timestamp":1777288500}