{
  "Old school bonds": true,
  "Energy potion": true,
  "Bronze arrow": true,
  "Bronze dart": true,
  "Iron arrow": true,
  "Iron dart": true,
  "Mind rune": true,
  "Steel arrow": true,
  "Steel dart": true,
  "Bass": true,
  "Bread": true,
  "Cake": true,
  "Cooked chicken": true,
  "Cooked meat": true,
  "Herring": true,
  "Lobster": true,
  "Mackerel": true,
  "Meat pie": true,
  "Pike": true,
  "Salmon": true,
  "Shrimps": true,
  "Tuna": true,
  "Ardougne teleport": true,
  "Camelot teleport": true,
  "Civitas illa fortis teleport": true,
  "Falador teleport": true,
  "Games necklace (8)": true,
  "Kourend castle teleport": true,
  "Lumbridge teleport": true,
  "Ring of dueling (8)": true,
  "Teleport to house": true,
  "Varrock teleport": true,
  "Chisel": true,
  "Gardening trowel": true,
  "Glassblowing pipe": true,
  "Hammer": true,
  "Needle": true,
  "Pestle and mortar": true,
  "Rake": true,
  "Saw": true,
  "Secateurs": true,
  "Seed dibber": true,
  "Shears": true,
  "Spade": true,
  "Watering can (0)": true
}
